Workbook

Sheet Descripciones
A1: CODIGO 2017 ALFANÚMERICO | B1: NOMBRE | C1: CODIGO 2017 ALFANÚMERICO | D1: CÓDIGO DE ÁREA 2017 | E1: AREA GENERAL | F1: SUBAREA | G1: ÁREA ESPECIFICA | H1: CÓDIGO NIVEL 2017 | I1: NIVEL ACTUAL( 2017) | J1: DESCRIPCION | K1: REPORTA A | L1: ESTUDIOS REQUERIDOS | M1: EXPERIENCIA REQUERIDA | N1: SEGUNDO IDIOMA
A2: CPAD00 | B2: PRESIDENTE - REGIONAL | C2: CPAD00 | D2: 4 | E2: CORPORATIVO | F2: ALTA DIRECCION | G2: REGIONAL | H2: 0 | I2: 1ER DIRECTIVO | J2: Planificar, organizar, dirigir y controlar todas las actividades de la compañía en una zona geográfica determinada cubriendo siempre más de un país. Identificar y recomendar la estrategia a corto, mediano y largo plazo, identificando y desarrollando nuevas oportunidades de negocio. Reporta generalmente a la Casa Matriz | K2: Casa matriz / Junta directiva | L2: Especialización | M2: Diversificada (15 años) | N2: Dominarlo
A3: CPAD03 | B3: GERENTE GENERAL | C3: CPAD03 | D3: 4 | E3: CORPORATIVO | F3: ALTA DIRECCION | G3: PAIS | H3: 0 | I3: 1ER DIRECTIVO | J3: Dirigir y hacer cumplir los planes generales de la empresa a través de los gerentes de cada área, para garantizar el aprovechamiento de los recursos humanos, financieros, materiales y tecnológicos en busca de los objetivos finales de la organización. | K3: Presidente / Junta directiva | L3: Especialización | M3: Más de 10 años | N3: Dominarlo
A4: CPAD01 | B4: PRESIDENTE PAIS | C4: CPAD01 | D4: 4 | E4: CORPORATIVO | F4: ALTA DIRECCION | G4: PAIS | H4: 0 | I4: 1ER DIRECTIVO | J4: Responsable de la dirección de una empresa a nivel nacional o local, con base en las orientaciones de una Junta Directiva o Casa Matriz. Es responsable de cumplir con la misión de la empresa y lograr sus objetivos fundamentales, mediante la definición y puesta en práctica de estratégias y políticas en todos sus ámbitos y la dirección de todas las áreas de la organización (comercial, operaciones, financiera, gestión humana, administración).El cargo requiere de un profesional con postgrado en un área afín a su cargo y amplia experiencia de negocios. Por lo general reporta a Casa Matriz. | K4: Junta directiva | L4: Especialización | M4: Diversificada (15 años) | N4: Dominarlo
A5: CPAD02 | B5: PRESIDENTE/ GERENTE GENERAL - PAIS | C5: CPAD02 | D5: 4 | E5: CORPORATIVO | F5: ALTA DIRECCION | G5: PAIS | H5: 0 | I5: 1ER DIRECTIVO | J5: Dirigir, planear y garantizar el cumplimiento de los resultados operacionales, comerciales y financieros de la compañía identificar y recomendar la estrategia a corto, mediano y largo plazo, identificando y desarrollando nuevas oportunidades de negocio. Máxima autoridad de la organización. | K5: Presidente / Junta directiva | L5: Especialización | M5: Diversificada (15 años) | N5: Dominarlo
A6: COVS10 | B6: VICEPRESIDENTE COMERCIAL | C6: COVS10 | D6: 3 | E6: COMERCIAL | F6: VENTAS | G6: VENTAS | H6: 1 | I6: EJECUTIVOS SR | J6: Formular y fijar las políticas comerciales de la entidad, dirigidas a las diferentes regionales, sucursales y agencias que existen en todo el país. Planear, dirigir y controlar la promoción y difusión de los diferentes productos y la adecuada prestación de los servicios existentes. | K6: Presidente / Gerente general | L6: Especialización | M6: Varias Especialidades (10 años) | N6: Dominarlo
A7: SGSN10 | B7: VICEPRESIDENTE SINIESTROS | C7: SGSN10 | D7: 22 | E7: SERVICIOS FINANCIEROS Y SEGUROS | F7: SINIESTROS | G7: SINIESTROS | H7: 1 | I7: EJECUTIVOS SR | J7: Define los parámetros operativos, estableciendo prioridades de recuperación de siniestros de terceros, reaseguros y coseguros. Mantiene contacto con otras compañías, buscando agilizar los procesos de resarcimiento para la empresa. Define también la posición de su compañía como líder o coaseguradora dentro de las propuestas de negocio. Acompaña la evolución de los procesos de resarcimiento / recuperación de los siniestros causados por terceros. Controla índices generales de siniestralidad de la Cia., priorizando la agilización de la atención de los pedidos de indemnización. | K7: Presidente | L7: Especialización | M7: Varias Especialidades (10 años) | N7: Dominarlo
A8: EDRT10 | B8: RECTOR | C8: EDRT10 | D8: 20 | E8: SERVICIOS EDUCATIVOS | F8: RECTORIA | G8: SERVICIOS EDUCATIVOS | H8: 1 | I8: EJECUTIVOS SR | J8: Planea, dirigir y soportar la gestión de docencia, investigación, proyección social y bienestar universitario, mediante una organización administrativa eficiente en el manejo de los recursos humanos, físicos, técnicos y financieros, que provea a los alumnos y profesores las mejores condiciones para su desarrollo académico. | K8: Junta directiva | L8: Especialización | M8: Más de 10 años | N8: Dominarlo
A9: COSC12 | B9: VICEPRESIDENTE SERVICIOS AL CLIENTE | C9: COSC12 | D9: 3 | E9: COMERCIAL | F9: SERVICIO AL CLIENTE | G9: SERVICIO AL CLIENTE | H9: 1 | I9: EJECUTIVOS SR | J9: Dirige la función de Servicio al Cliente. Responsable por establecer políticas y procedimientos para proveer soporte técnico y no técnico a los clientes de acuerdo con las obligaciones contractuales. Puede ser responsable por desarrollar y vigilar la implementacion de estrategias de fidelizacion y satisfaccion. | K9: Presidente | L9: Especialización | M9: Varias Especialidades (10 años) | N9: Dominarlo
A10: FISR10 | B10: VICEPRESIDENTE GERENCIAMENTO RIESGO | C10: FISR10 | D10: 5 | E10: FINANCIERA | F10: SEGUROS / RIESGO FINANCIERO | G10: RIESGO | H10: 1 | I10: EJECUTIVOS SR | J10: Responsable de implementar y dirigir la evaluación y administración de todos los riesgos a los que pueden estar expuestos las instalaciones, inventarios y otras propiedades de la compañía, tales como inspecciones de riesgos, los estados financieros y de planeacion. | K10: Presidente | L10: Especialización | M10: Varias Especialidades (10 años) | N10: Dominarlo
A11: MAPR10 | B11: VICEPRESIDENTE MANUFACTURA | C11: MAPR10 | D11: 11 | E11: MANUFACTURA E INDUSTRIA | F11: PRODUCCION | G11: PRODUCCION | H11: 1 | I11: EJECUTIVOS SR | J11: Responder por todas las operaciones de fabricación, mantenimiento y proyectos en una empresa o grupo de empresas. Informar al presidente de la compañía; tiene a su cargo los gerentes o superintendentes de las diversas plantas o áreas. | K11: Presidente | L11: Especialización | M11: Varias Especialidades (10 años) | N11: Dominarlo
A12: MAGN10 | B12: VICEPRESIDENTE MANUFACTURA | C12: MAGN10 | D12: 11 | E12: MANUFACTURA E INDUSTRIA | F12: PRODUCCION | G12: PRODUCCION | H12: 1 | I12: EJECUTIVOS SR | J12: Otros Nombres: Vicepresidente de Manufactura, Vicepresidente de Producción, Vicepresidente de Operaciones de Planta. Responsable de las estrategias de manufactura de la empresa en el ámbito nacional o local, con base en las orientaciones de la Presidencia/Gerente General. Dirige los procesos productivos de los distintos centros o plantas de producción. Evalúa las oportunidades de desarrollo tecnológico y lleva a cabo proyectos de mejoramiento y expansión. Se requiere un profesional con postgrado en un área afín a su cargo y amplia experiencia en su campo. Reporta a: Presidente. | K12: Presidente | L12: Especialización | M12: Varias Especialidades (10 años) | N12: Dominarlo
A13: CPAD10 | B13: VICEPRESIDENTE EJECUTIVO | C13: CPAD10 | D13: 4 | E13: CORPORATIVO | F13: ALTA DIRECCION | G13: PAIS | H13: 1 | I13: EJECUTIVOS SR | J13: Coordinar la ejecución de estrategias y políticas generales, dirigidas a obtener el mejor aprovechamiento de los recursos, el desarrollo de la institución y responder por la gestión de todas las áreas a su cargo, de tal forma que se logren los objetivos finales de la organización. En ausencia del Presidente, asume las funciones y representa a la entidad tanto interna como externamente. | K13: Presidente | L13: Especialización | M13: Varias Especialidades (10 años) | N13: Dominarlo
... A33: ATVT10 | B33: VICEPRESIDENTE VENTAS ALTA TECNOLOGÍA (GENÉRICO) | C33: ATVT10 | D33: 16 | E33: ALTA TECNOLOGÍA Y TELECOMUNICACIONES | F33: VENTAS | G33: Alta Tecnología | H33: 1 | I33: EJECUTIVOS SR | J33: Responsable por el logro de los objetivos de ventas de una región ó zona muy significativa. Desarrolla e implementa todas las estrategias organizacionales y del negocio para el departamento, incluyendo la asignación de territorios ó productos, formulación de soluciones. | K33: Presidente | L33: Especialización | M33: Varias Especialidades (10 años) | N33: Dominarlo
A34: SGSC10 | B34: VICEPRESIDENTE SUSCRIPCIÓN | C34: SGSC10 | D34: 22 | E34: SERVICIOS FINANCIEROS Y SEGUROS | F34: SUSCRIPCION | G34: 0 | H34: 1 | I34: EJECUTIVOS SR | J34: Dirige y controla el proceso de Suscripción en los ramos de Personas, Auto, Patrimoniales y Riesgos industriales, a nivel nacional, velando porque se cumplan con las disposiciones legales establecidas por la Superintendencia de Seguros, las políticas y lineamientos de la organización y los condicionados de las pólizas, con la finalidad de controlar la siniestralidad y ofrecer una respuesta oportuna a los asegurados. | K34: Presidente | L34: Especialización | M34: Varias Especialidades (10 años) | N34: Dominarlo
A35: ATAT10 | B35: VICEPRESIDENTE TECNICO TELECOMINICACIONES | C35: ATAT10 | D35: 16 | E35: ALTA TECNOLOGÍA Y TELECOMUNICACIONES | F35: 0 | G35: 0 | H35: 1 | I35: EJECUTIVOS SR | J35: Planear y dirigir todo lo relacionado con el mantenimiento de la red nacional y de las estaciones de servicio. Definir estrategias a seguir para la elaboración de proyectos de construcción o ampliación de nuevas estaciones. | K35: Presidente | L35: Especialización | M35: Varias Especialidades (10 años) | N35: Dominarlo
A36: EDRT20 | B36: VICERECTOR ACADEMICO | C36: EDRT20 | D36: 20 | E36: SERVICIOS EDUCATIVOS | F36: RECTORIA | G36: SERVICIOS EDUCATIVOS | H36: 2 | I36: EJECUTIVOS | J36: Definir las políticas académicas de la institución, velando por la calidad de los programas que se ofrecen, así mismo, dirigir programas para la actualización docente, supervisar la creación de programas tanto de pregrado como de postgrado, certificar los reportes académicos ante el ICFES. | K36: Rector | L36: Especialización | M36: Más de 10 años | N36: Dominarlo
A37: COSC22 | B37: VICEPRESIDENTE SERVICIO AL CLIENTE | C37: COSC22 | D37: 3 | E37: COMERCIAL | F37: SERVICIO AL CLIENTE | G37: SERVICIO AL CLIENTE | H37: 2 | I37: EJECUTIVOS | J37: Definir las políticas de trabajo y los planes de acción necesarios, en la búsqueda del mejoramiento continuo de los índices de gestión de calidad de atención del cliente externo. | K37: Presidente / Gerente general | L37: Especialización | M37: Varias Especialidades (10 años) | N37: Dominarlo
A38: GHGN20 | B38: VICEPRESIDENTE GESTION HUMANA | C38: GHGN20 | D38: 6 | E38: GESTIÓN HUMANA | F38: GENERAL | G38: RECURSOS HUMANOS | H38: 2 | I38: EJECUTIVOS | J38: Formular y controlar el cumplimiento de políticas de administración de Recursos Humanos. Asesorar al gerente en materia de selección, evaluación del desempeño, administración salarial, bienestar social y relaciones laborales a fin de garantizar el desarrollo del recurso humano. | K38: Presidente | L38: Especialización | M38: Varias Especialidades (10 años) | N38: Dominarlo
A39: MKMP20 | B39: VICEPRESIDENTE MERCADEO | C39: MKMP20 | D39: 12 | E39: MERCADEO | F39: MARCAS Y PRODUCTOS | G39: MERCADEO | H39: 2 | I39: EJECUTIVOS | J39: Dirigir, planear y coordinar la ejecución de las estrategias de mercadeo para la compañía, garantizando que los productos y servicios sean de buena calidad y aceptación, procurar que su rentabilidad y permanencia sean adecuadas. | K39: Presidente / Gerente general | L39: Especialización | M39: Varias Especialidades (10 años) | N39: Dominarlo
A40: JULE20 | B40: GERENTE JURÍDICO CORPORATIVO | C40: JULE20 | D40: 8 | E40: JURÍDICA | F40: LEGAL | G40: LEGAL | H40: 2 | I40: EJECUTIVOS | J40: Responsable de la orientación legal de la compañía, asegurando la conformidad con la legislación actual, vigilando los derechos y obligaciones. Guía el trabajo de los abogados especializados y/o despachos de consultoría, incluyendo contratos, marcas y patentes. | K40: Vicepresidente jurídico | L40: Especialización | M40: Más de 10 años | N40: Dominarlo
A41: MAGN20 | B41: GERENTE TÉCNICO | C41: MAGN20 | D41: 11 | E41: MANUFACTURA E INDUSTRIA | F41: INGENIERIA | G41: INGENIERIA | H41: 2 | I41: EJECUTIVOS | J41: Responsable de establecer las especificaciones técnicas de los procesos, productos y/o servicios de la compañía para asegurar su aplicación, lo que implica dirigir las actividades de ingeniería, calidad, proyectos y otras actividades relacionadas. | K41: Gerente general | L41: Especialización | M41: Más de 10 años | N41: Dominarlo
A42: FIGN20 | B42: GERENTE ADMINISTRATIVO Y FINANCIERO | C42: FIGN20 | D42: 5 | E42: FINANCIERA | F42: GENERAL | G42: GENERAL | H42: 2 | I42: EJECUTIVOS | J42: Diseñar, direccionar, coordinar y controlar las políticas administrativas y financieras, supervisar y controlar los procesos productivos de los recursos financieros, humanos, de información y servicios generales para el cumplimiento de los objetivos empresariales. | K42: Vicepresidente administrativo | L42: Especialización | M42: Más de 10 años | N42: Dominarlo
A43: ADGN20 | B43: VICEPRESIDENTE ADMINISTRATIVO | C43: ADGN20 | D43: 1 | E43: ADMINISTRATIVA | F43: GENERAL | G43: GENERAL | H43: 2 | I43: EJECUTIVOS | J43: Diseñar, dirigir, coordinar y controlar las políticas administrativas, supervisar y controlar la estructura organizacional, procesos productivos del personal, presupuestos y seguros. Así mismo vela por la optimización tecnológica o informática y busca el mejoramiento del área de servicios generales, garantizar el cumplimiento de los objetivos de la empresa. | K43: Presidente | L43: Especialización | M43: Varias Especialidades (10 años) | N43: Dominarlo
A44: LSGN20 | B44: VICEPRESIDENTE LOGÍSTICA | C44: LSGN20 | D44: 10 | E44: LOGÍSTICA Y SUMINISTROS | F44: GENERAL | G44: GENERAL | H44: 2 | I44: EJECUTIVOS | J44: Responsable de las estrategias de logística de la empresa a nivel nacional o local, con base en la orientaciones del Presidente / Gerente General. Define las políticas de gastos del área de logística; Señala las políticas para el suministro de materias primas, productos o servicios, manejo de los inventarios y suministro de productos a los clientes. Establece las políticas y normas para la selección de proveedores a nivel nacional e internacional. Se requiere un profesional con postgrado en un área afín a su cargo y amplia experiencia en su campo. Reporta a: Presidente. | K44: Presidente | L44: Especialización | M44: Varias Especialidades (10 años) | N44: Dominarlo
A45: FQCH20 | B45: GERENTE GRUPO PRODUCTOS - HOSPITAL /ESPECIALIDADES | C45: FQCH20 | D45: 21 | E45: QUÍMICO Y FARMA | F45: HOSPITALARIA | G45: Farmacéutica | H45: 2 | I45: EJECUTIVOS | J45: Responsable de la planeación, coordinación y definición de los objetivos de venta, estrategias de mercadotecnia, análisis de rentabilidad, potencial de mercado, competencia, promoción y otras actividades de mercadotecnia para un grupo de productos Hospitalarios. | K45: Gerente general | L45: Especialización | M45: Más de 10 años | N45: Dominarlo
A46: FQCF20 | B46: GERENTE MEDICO GRUPO PRODUCTOS | C46: FQCF20 | D46: 21 | E46: QUÍMICO Y FARMA | F46: COMERCIAL FARMA | G46: Farmacéutica | H46: 2 | I46: EJECUTIVOS | J46: Responsable de la implementación de procedimientos para la revisión científica del material de mercadotecnia, etiquetas, protocolos y estudios para un grupo o línea de productos. Puede actuar como representante de la compañía, de esta línea específica de productos. | K46: Vicepresidente médico | L46: Especialización | M46: Más de 10 años | N46: Dominarlo
A47: CPPL20 | B47: VICEPRESIDENTE PLANEACION | C47: CPPL20 | D47: 4 | E47: CORPORATIVO | F47: PLANEACION | G47: CORPORATIVO | H47: 2 | I47: EJECUTIVOS | J47: Definir estrategias para la organización, evaluar opciones de crecimiento; coordinar las actividades de banca de inversión y seguir de cerca los intereses de la organización en otras empresas. Dirigir y coordinar la realización de proyectos desde el análisis de tecnología hasta el desarrollo de nuevos productos y/o servicios. | K47: Presidente | L47: Especialización | M47: Varias Especialidades (10 años) | N47: Dominarlo
... A49: AAAU20 | B49: VICEPRESIDENTE CONTRALOR | C49: AAAU20 | D49: 2 | E49: AUDITORIA | F49: AUDITORIA | G49: AUDITORIA | H49: 2 | I49: EJECUTIVOS | J49: Coordinar, dirigir y controlar las normas procedimientos y flujo de información contable y financiera tendientes a proteger en forma adecuada los activos e intereses económicos de la entidad. Asesorar a los demás ejecutivos en cuanto a procedimientos, control y manejo de sus áreas para el buen funcionamiento de las mismas. | K49: Presidente | L49: Especialización | M49: Varias Especialidades (10 años) | N49: Dominarlo
A50: HEPE20 | B50: GERENTE PERFORACION | C50: HEPE20 | D50: 23 | E50: MINERIA, ENERGIA E HIDROCARBUROS | F50: PERFORACION | G50: 0 | H50: 2 | I50: EJECUTIVOS | J50: Diseñar, planear y coordinar las actividades del programa de perforación con el fin de alcanzar éxito económico en las operaciones y el logro de los objetivos empresariales. | K50: Gerente general | L50: Especialización | M50: Más de 10 años | N50: Dominarlo
A51: SGSC20 | B51: VICEPRESIDENTE SUSCRIPCIÓN | C51: SGSC20 | D51: 22 | E51: SERVICIOS FINANCIEROS Y SEGUROS | F51: SUSCRIPCION | G51: 0 | H51: 2 | I51: EJECUTIVOS | J51: Diseñar e implementar las políticas y estratégias de comercialización y suscripción de las diferentes ramas de seguros, desarrolla productos y busca optimizar los servicios a los clientes con el objetivo de alcanzar las metas establecidas por la dirección general. | K51: Presidente | L51: Especialización | M51: Varias Especialidades (10 años) | N51: Dominarlo
A52: SGID20 | B52: VICEPRESIDENTE TECNICO INDEMNIZACIONES | C52: SGID20 | D52: 22 | E52: SERVICIOS FINANCIEROS Y SEGUROS | F52: INDEMNIZACIONES | G52: 0 | H52: 2 | I52: EJECUTIVOS | J52: Asegurar el cumplimiento de los estándares corporativos relacionados con: servicio, constitutivos de reservas, pagos de indemnizaciones, ajustes, investigación y administración de asesores externos. Es responsable por la planeación dirección y control de las operaciones, así como la adecuada documentación de reclamos. Se encarga de asegurar el control y eficacia de las acciones de recobros y de la conservación y renta de salvamentos. Representa a la compañía en cualquier proceso legal originado en las actividades de reclamaciones. | K52: Presidente | L52: Especialización | M52: Varias Especialidades (10 años) | N52: Dominarlo
A53: COVS30 | B53: GERENTE COMERCIAL | C53: COVS30 | D53: 3 | E53: COMERCIAL | F53: VENTAS | G53: VENTAS | H53: 3 | I53: GERENTES SR | J53: Planear, dirigir y controlar una línea específica de productos, evaluar el grado de satisfacción del consumidor. Dar apoyo en la fijación de políticas de comercialización. | K53: Vicepresidente comercial/Gerente general | L53: Especialización | M53: Especializada (7 a 9 años) | N53: Dominarlo
A54: COSC33 | B54: GTE TELEMARKETING | C54: COSC33 | D54: 3 | E54: COMERCIAL | F54: SERVICIO AL CLIENTE | G54: TELEMARKETING | H54: 3 | I54: GERENTES SR | J54: Gerencia la ejecución de las actividades en la unidad de telemarketing pasivo, que brinda atención a clientes en asuntos ligados a los productos y servicios comercializados por la empresa. Gerencia, además, procesos de telemarketing activo, buscando conseguir nuevos clientes, de acuerdo con la política comercial preestablecida. Desarrolla el equipo de operadores, buscando capacitarlos para dar una correcta atención al cliente, así como para optimizar la política de expansión y conquista de nuevos clientes y el grado del relación cliente-empresa. | K54: Vicepresidente Servicio al cliente | L54: Especialización | M54: Especializada (7 a 9 años) | N54: Dominarlo
A55: GHSE30 | B55: GERENTE RECLUTAMIENTO Y SELECCIÓN | C55: GHSE30 | D55: 6 | E55: GESTIÓN HUMANA | F55: SELECCION | G55: SELECCION | H55: 3 | I55: GERENTES SR | J55: Responsable de las definiciones y estrategias del área de reclutamiento y selección, con el objetivo de atraer a profesionales competentes y preparados, identificando, interna y externamente, los recursos humanos adecuados para ocupar las posiciones solicitadas. | K55: Gerente Gestión Humana | L55: Especialización | M55: Especializada (7 a 9 años) | N55: Dominarlo
A56: JUSG30 | B56: SECRETARIO GENERAL | C56: JUSG30 | D56: 8 | E56: JURÍDICA | F56: SECRETARIA GENERAL | G56: SECRETARIA GENERAL | H56: 3 | I56: GERENTES SR | J56: Apoyar y coordinar los aspectos administrativos tanto de la Junta Directiva como de la Asamblea General de Accionistas, elaborar la documentación y actas correspondientes bajo las normas legales y estatutarias que rigen la entidad. | K56: Presidente | L56: Especialización | M56: Especializada (7 a 9 años) | N56: Dominarlo
A57: FISR30 | B57: GERENTE RIESGOS | C57: FISR30 | D57: 5 | E57: FINANCIERA | F57: SEGUROS / RIESGO FINANCIERO | G57: RIESGO | H57: 3 | I57: GERENTES SR | J57: Planear, dirigir, coordinar y controlar las políticas de riesgo de mercado en el corto, mediano y largo plazo, teniendo en cuenta las variables y análisis técnicos y fundamentales del mercado, con el fin de recomendar los instrumentos de inversión para maximizar el valor de los accionistas. | K57: Vicepresidente de Gerenciamiento del riesgo | L57: Especialización | M57: Especializada (7 a 9 años) | N57: Dominarlo
A58: TIIR30 | B58: GTE INFRAESTRUCTURA | C58: TIIR30 | D58: 9 | E58: TECNOLOGÍA E INFORMÁTICA | F58: INFRAESTRUCTURA REDES BASES DATOS | G58: REDES BASES DE DATOS | H58: 3 | I58: GERENTES SR | J58: Responde por el planeamiento, desarrollo y control de las redes de telecomunicaciones (voz, datos y mensajes). Dimensiona la capacidad de operación de la red dentro de los niveles de performance y calidad establecidos. Coordina la alocación de los recursos de telecomunicaciones de acuerdo con las necesidades de cada segmento de la empresa. Controla la calidad de los canales y la correcta observación de los estándares y procedimientos definidos. Evalúa riesgos y establece los planes de contingencia de la unidad. | K58: Vicepresidente sistemas / Gerente general | L58: Especialización | M58: Especializada (7 a 9 años) | N58: Dominarlo
A59: GHGN30 | B59: GERENTE GESTION HUMANA | C59: GHGN30 | D59: 6 | E59: GESTIÓN HUMANA | F59: GENERAL | G59: RECURSOS HUMANOS | H59: 3 | I59: GERENTES SR | J59: Planear, dirigir y evaluar las políticas de administración de personal, capacitación, desarrollo y bienestar. Asesorar a los demás ejecutivos en lo pertinente a su área y supervisar a los ejecutivos de recursos humanos de cada una de las plantas o filiales de su organización. | K59: Presidente / Gerente general | L59: Especialización | M59: Especializada (7 a 9 años) | N59: Dominarlo
A60: IDPR30 | B60: GERENTE DESARROLLO PRODUCTOS | C60: IDPR30 | D60: 7 | E60: I & D | F60: DESARROLLO DE PRODUCTOS | G60: PRODUCTOS | H60: 3 | I60: GERENTES SR | J60: Responsable de las actividades relacionadas con el desarrollo de un producto o línea de productos, así como de las mejoras a los productos y tecnologías existentes. Da seguimiento junto con la casa matriz a la evolución tecnológica y evalúa las posibilidad de implementacion. | K60: Gerente Investigación y Desarrollo | L60: Especialización | M60: Especializada (7 a 9 años) | N60: Dominarlo
A61: MAPR30 | B61: GERENTE PRODUCCION | C61: MAPR30 | D61: 11 | E61: MANUFACTURA E INDUSTRIA | F61: PRODUCCION | G61: PRODUCCION | H61: 3 | I61: GERENTES SR | J61: Planear, programar y controlar la producción desde la sección que recibe la materia prima hasta la que entrega a las bodegas el producto terminado. | K61: Vicepresidente manufactura / gerente técnico | L61: Especialización | M61: Especializada (7 a 9 años) | N61: Dominarlo
A62: MAPM30 | B62: GERENTE PROCESOS | C62: MAPM30 | D62: 11 | E62: MANUFACTURA E INDUSTRIA | F62: PROCESOS MANUFACTURA | G62: PROCESOS MANUFACTURA | H62: 3 | I62: GERENTES SR | J62: Responsable del desarrollo, implementación y seguimiento de las mejoras en los métodos / procesos de las líneas de producción. Optimiza el uso de mano de obra, tiempo normal, material, equipo y energía, soluciona problemas en el proceso de manufactura. | K62: Gerente producción / planta | L62: Especialización | M62: Especializada (7 a 9 años) | N62: Dominarlo
A63: MAPP30 | B63: GERENTE PLANEACION Y CONTROL PRODUCCIÓN | C63: MAPP30 | D63: 11 | E63: MANUFACTURA E INDUSTRIA | F63: PLANEACION PRODUCCION | G63: PLANEACION PRODUCION | H63: 3 | I63: GERENTES SR | J63: Responsable de la adecuada planeación de producción, manteniendo un estricto control de los materiales de producción y de los productos terminados o semiterminados. Maneja a los empleados en la entrega oportuna de materiales, la preparación de programas de producion. | K63: Vicepresidente de manufactura | L63: Especialización | M63: Especializada (7 a 9 años) | N63: Dominarlo
A64: TIOS30 | B64: GERENTE OPERACIÓN SISTEMAS | C64: TIOS30 | D64: 9 | E64: TECNOLOGÍA E INFORMÁTICA | F64: OPERACIONES SISTEMAS | G64: OPERACIONES SISTEMAS | H64: 3 | I64: GERENTES SR | J64: Responsable de programar la carga de trabajo del procesamiento electrónico de información y de emitir los reportes solicitados por las diferentes áreas de la compañía. Le da continuidad a las operaciones del sistema, controlando y garantizando todas operaciones de sistemas de la entidad. | K64: Vicepresidente sistemas / Gerente general | L64: Especialización | M64: Especializada (7 a 9 años) | N64: Dominarlo
... A98: COAV30 | B98: GERENTE ADMINISTRACIÓN VENTAS | C98: COAV30 | D98: 3 | E98: COMERCIAL | F98: ADMINISTRACION Y PLANEACION VENTAS | G98: ADMINISTRACION Y PLANEACION VENTAS | H98: 3 | I98: GERENTES SR | J98: Responsable de manejar la administración de los contratos de venta y servicios y de la logística comercial; centro de enlace entre vendedores y clientes, responde a cuestionamientos de las órdenes de existencias y envíos. Generar reportes y estadísticas de ventas. | K98: Vicepresidente comercial | L98: Especialización | M98: Especializada (7 a 9 años) | N98: Dominarlo
A99: HEAD30 | B99: DIRECTOR HSEQ | C99: HEAD30 | D99: 23 | E99: MINERIA, ENERGIA E HIDROCARBUROS | F99: ADMINISTRATIVO | G99: 0 | H99: 3 | I99: GERENTES SR | J99: Dirigir la gestión de calidad e integridad de los proyectos de hidrocarburos con el fin de garantizar mejoramientos de las condiciones y la efectividad de los procesos de explotacion y exploración de la compañía | K99: Gerente exploración | L99: profesional | M99: De 6 a 8 años | N99: Comunicarse
A100: CTAD30 | B100: GERENTE CONSTRUCCIONES | C100: CTAD30 | D100: 18 | E100: CONSTRUCCIÓN E INSUMOS | F100: ADMINISTRATIVA | G100: 0 | H100: 3 | I100: GERENTES SR | J100: Gerenciar los procesos de construcción y montaje, y las áreas de producción, planificación y costos. | K100: Gerente general / Presidente | L100: Profesional | M100: De 8 a 10 años | N100: No requiere
A101: HEMT30 | B101: GERENTE INGENIERIA | C101: HEMT30 | D101: 23 | E101: MINERIA, ENERGIA E HIDROCARBUROS | F101: MANTENIMIENTO | G101: 0 | H101: 3 | I101: GERENTES SR | J101: Evaluar reservas de campo y perforación exploratoria para justificar el desarrollo de nuevas inversiones. Dirigir los estudios de yacimientos para optimizar la recuperación de los campos en explotación. | K101: Gerente general | L101: Especialización | M101: Especializada (7 a 9 años) | N101: Dominarlo
A102: HEEX30 | B102: GERENTE PROYECTOS - HIDROCARBUROS | C102: HEEX30 | D102: 23 | E102: MINERIA, ENERGIA E HIDROCARBUROS | F102: EXPLORACION | G102: 0 | H102: 3 | I102: GERENTES SR | J102: Administrar los proyectos asignados para que se ejecuten dentro de los presupuestos, plazos y políticas. Propone nuevos proyectos para mejorar las condiciones de los procesos y el transporte de hidrocarburos. | K102: Gerente General / Presidente | L102: Especialización | M102: Especializada (7 a 9 años) | N102: Dominarlo
A103: COVS40 | B103: GERENTE CUENTA | C103: COVS40 | D103: 3 | E103: COMERCIAL | F103: VENTAS | G103: VENTAS | H103: 4 | I103: GERENTES | J103: Responsable del proceso de ventas directas en cuentas pequeñas y esta a cargo de la expansión de las ventas, introduciendo nuevos productos y servicios a través de visitas a clientes actuales y potenciales. Requiere una experiencia de 2 a 3 años. Reporta a: Gerente General de Ventas | K103: Gerente de ventas | L103: Profesional | M103: Especializada (7 a 9 años) | N103: Dominarlo
A104: COVS42 | B104: GERENTE VENTAS | C104: COVS42 | D104: 3 | E104: COMERCIAL | F104: VENTAS | G104: VENTAS | H104: 4 | I104: GERENTES | J104: Comercializar los productos o servicios que vende la empresa. Tiene a su cargo varios gerentes de distrito o sucursales o supervisores de ventas en los cuales delega el control de los vendedores o representantes de ventas. Es además el encargado de la planeación y ejecución del presupuesto de ventas y mantiene las relaciones comerciales con los distribuidores y clientes más importantes. | K104: Gerente de mercadeo / Gerente comercial | L104: Profesional | M104: Especializada (7 a 9 años) | N104: Dominarlo
A105: CMVT40 | B105: GERENTE TRADE MKARKETING | C105: CMVT40 | D105: 19 | E105: CONSUMO MASIVO | F105: VENTAS | G105: TRADE MARKETING | H105: 4 | I105: GERENTES | J105: Responsable por estructurar los precios al por menor con margen comercial. También responde por la eficaz estrategia de marketing, con márgenes de rentabilidad para todos los negocios comerciales y cuentas clave. Fijar todos los márgenes comerciales, comisiones, etc y todas las actividades de gestión. Profesional con especialidad Comercial y más de 10 años de experiencia. | K105: Vicepresidente comercial | L105: Profesional | M105: Especializada (7 a 9 años) | N105: Dominarlo
A106: FITS40 | B106: GERENTE TESORERIA - TESORERO | C106: FITS40 | D106: 5 | E106: FINANCIERA | F106: TESORERIA | G106: TESORERIA | H106: 4 | I106: GERENTES | J106: Administrar los fondos e inversiones de la compañía, los créditos, seguros, pagos a proveedores, cartera y las relaciones con los organismos financieros y bancarios, a fin de garantizar el manejo eficiente de los recursos monetarios de la empresa. | K106: Gerente / Vicepresidente financiero | L106: Profesional | M106: Especializada (7 a 9 años) | N106: Dominarlo
A107: FNTJ40 | B107: DIRECTOR TARJETA DE CREDITO | C107: FNTJ40 | D107: 22 | E107: SERVICIOS FINANCIEROS Y SEGUROS | F107: TARJETAS | G107: TARJETAS | H107: 4 | I107: GERENTES | J107: Asignar nuevas tarjetas, con sus respectivos cupos, autorizar aumentos de cupo para tarjetas antiguas, coordinar la ejecución de programas de actualización de datos y determinar el envío de cuentas a la división jurídica, a fin de lograr calidad en el servicio al cliente. | K107: Vicepresidente crédito / Vicepresidente financiero | L107: Profesional | M107: Especializada (7 a 9 años) | N107: Dominarlo
A108: FNTJ41 | B108: GERENTE TARJETA CREDITO | C108: FNTJ41 | D108: 22 | E108: SERVICIOS FINANCIEROS Y SEGUROS | F108: TARJETAS | G108: TARJETAS | H108: 4 | I108: GERENTES | J108: Planear, dirigir, supervisar y coordinar los procesos de mercadeo para los servicios que prestan las tarjetas de crédito. Atender las relaciones con instituciones afines al ramo, diseñar estrategias para el saneamiento de cartera, el recaudo y mejoramiento de la seguridad. Mantener contacto con los clientes dando soluciones a reclamos y promocionando nuevos servicios. | K108: Vicepresidente crédito / Vicepresidente financiero | L108: Profesional | M108: Especializada (7 a 9 años) | N108: Dominarlo
A109: TIST40 | B109: GERENTE HELPDESK | C109: TIST40 | D109: 9 | E109: TECNOLOGÍA E INFORMÁTICA | F109: SOPORTE TECNICO | G109: SOPORTE TECNICO | H109: 4 | I109: GERENTES | J109: Responsable por coordinar las actividades específicas relacionadas con la Tecnología de la Información (TI) en la compañía hechas por teléfono, comprendiendo la definición, desarrollo, mantenimiento y operación de los sistemas, así como mantener el nivel | K109: Gerente Sistemas / Vicepresidente sistemas | L109: Profesional | M109: Especializada (7 a 9 años) | N109: Dominarlo
A110: ADSG40 | B110: GERENTE SERVICIOS GENERALES | C110: ADSG40 | D110: 1 | E110: ADMINISTRATIVA | F110: SERVICIOS GENERALES | G110: SERVICIOS GENERALES | H110: 4 | I110: GERENTES | J110: Planear, dirigir y coordinar los procesos de compras, manejo de almacén y distribución de papelería en todas las dependencias de la organización, supervisar el correcto funcionamiento de los servicios de cafetería, transporte, aseo, coordinar el archivo y las reparaciones locativas menores, así como los servicios de vigilancia y seguridad. | K110: Vicepresidente administrativo o recursos humanos | L110: Profesional | M110: Especializada (7 a 9 años) | N110: Dominarlo
A111: EDIV40 | B111: DIRECTOR INVESTIGACIÓN | C111: EDIV40 | D111: 20 | E111: SERVICIOS EDUCATIVOS | F111: INVESTIGACION | G111: SERVICIOS EDUCATIVOS | H111: 4 | I111: GERENTES | J111: Coordina, controla y promueve las investigaciones que se desarrollan en la universidad por los estudiantes, profesionales, docentes con el ánimo de promover la actividad investigativa de los diferentes programas. Establece las pautas y normas para desarrollar proyectos, monografías y/ó tesis que garanticen la formación académica de los investigadores y su selección como trabajos que representen a la universidad en eventos investigativos. El cargo es ocupado por un profesional con 3 años de experiencia. | K111: Rector / Director administrativo | L111: Profesional | M111: Especializada (7 a 9 años) | N111: Dominarlo
A112: EDPG40 | B112: DIRECTOR POSTGRADO | C112: EDPG40 | D112: 20 | E112: SERVICIOS EDUCATIVOS | F112: POSTGRADOS | G112: SERVICIOS EDUCATIVOS | H112: 4 | I112: GERENTES | J112: Coordinar los planes y programas de las especializaciones, velando por la inclusión de cátedras que respondan a las necesidades del mercado con el fin de garantizar calidad en los programas bajo su control. | K112: Decano | L112: Profesional | M112: Especializada (7 a 9 años) | N112: Dominarlo
A113: EDCL40 | B113: RECTOR COLEGIO | C113: EDCL40 | D113: 20 | E113: SERVICIOS EDUCATIVOS | F113: COLEGIO | G113: SERVICIOS EDUCATIVOS | H113: 4 | I113: GERENTES | J113: Planea, dirigir y soportar la gestión de docencia, investigación y bienestar del colegio.Reponde por el eficiente manejo administrativo en cuanto a recursos humanos, físicos, técnicos y financieros. Reporta a Consejo Directivo | K113: Junta directiva | L113: Profesional | M113: Especializada (7 a 9 años) | N113: Dominarlo
A114: COSC42 | B114: GERENTE SERVICIO AL CLIENTE | C114: COSC42 | D114: 3 | E114: COMERCIAL | F114: SERVICIO AL CLIENTE | G114: SERVICIO AL CLIENTE | H114: 4 | I114: GERENTES | J114: Dirigir, planear y controlar las estrategias de servicio de la compañía para garantizar la calidad del servicio al cliente de una manera efectiva. | K114: Gerente general / Presidente | L114: Profesional | M114: Especializada (7 a 9 años) | N114: Dominarlo
... A164: TIGN41 | B164: GERENTE SOPORTE Y TECNOLOGIA | C164: TIGN41 | D164: 9 | E164: TECNOLOGÍA E INFORMÁTICA | F164: GENERAL | G164: GENERAL | H164: 4 | I164: GERENTES | J164: Responder por los criterios, procedimientos y políticas de seguimiento de los productos y servicios a nivel tecnológico. Interpretar y ejecutar la propuesta realizada por la gerencia de planeación. Dar soporte técnico/tecnológico a nivel de servicios de red y participar en la generación de nuevos productos, futuras tecnologías y mejoramiento de la actual. | K164: Vicepresidente sistemas / Gerente general | L164: Profesional | M164: Especializada (7 a 9 años) | N164: Dominarlo
A165: FIPC411 | B165: DIRECTOR FINANCIERO | C165: FIPC411 | D165: 5 | E165: FINANCIERA | F165: GENERAL | G165: GENERAL | H165: 4 | I165: DIRECTORES | J165: Dirigir y hacer seguimiento a la Gestión Financiera de la organización con el fin de garantizar la confiabilidad y oportunidad de la información financiera, la consecución de los recursos económicos necesarios, a través del manejo racional y óptimo de los fondos requeridos y asegurando el cumplimiento de los objetivos propuestos
A166: FNFD40 | B166: DIRECTOR FONDO COMUN | C166: FNFD40 | D166: 22 | E166: SERVICIOS FINANCIEROS Y SEGUROS | F166: FIDUCIARIA | G166: FIDUCIARIA | H166: 4 | I166: GERENTES | J166: Responder por el manejo de la operación diaria de portafolios. Coordinar, manejar y controlar todo lo relacionado con el fondo común; debe buscar dentro de las políticas de crédito de la fiduciaria las mejores alternativas de inversión en el mercado, procurando la mejor rentabilidad. Volumen del fondo entre: 10000 y 20000 millones de pesos. | K166: Vicepresidente financiero / Gerente general | L166: Profesional | M166: Especializada (7 a 9 años) | N166: Dominarlo
A167: FNFD41 | B167: GERENTE PRODUCTO O NEGOCIO FIDUCIARIO | C167: FNFD41 | D167: 22 | E167: SERVICIOS FINANCIEROS Y SEGUROS | F167: FIDUCIARIA | G167: FIDUCIARIA | H167: 4 | I167: GERENTES | J167: Asesorar y atender los clientes inversionistas de los diferentes proyectos en un producto específico de la fiduciaria. Representar a la fiduciaria en el manejo de los productos asignados. Consigue nuevos clientes para su negocio y administra uno o varios negocios. | K167: Gerente Financiero / Presidente | L167: Profesional | M167: Especializada (7 a 9 años) | N167: Dominarlo
A168: FQID40 | B168: GERENTE INVESTIGACIÓN CLÍNICA | C168: FQID40 | D168: 21 | E168: QUÍMICO Y FARMA | F168: INVESTIGACION Y DESARROLLO | G168: Farmacéutica | H168: 4 | I168: GERENTES | J168: Responsable del diseño, planeación e implementación de las pruebas / proyectos de investigación clínica de mediana complejidad. Conduce visitas de observación en el campo. Asegura que se cumplan los protocolos y los objetivos generales de investigación. Medico especializado. | K168: Vicepresidente Investigación Clínica | L168: Profesional | M168: Especializada (7 a 9 años) | N168: Dominarlo
A169: FQCH41 | B169: GERENTE PRODUCTO - HOSPITAL /ESPECIALIDADES | C169: FQCH41 | D169: 21 | E169: QUÍMICO Y FARMA | F169: HOSPITALARIA | G169: Farmacéutica | H169: 4 | I169: GERENTES | J169: Responsable de la planeación, coordinación y definición de los objetivos de venta, estrategias de mercadotecnia, análisis de rentabilidad, potencial de mercado, competencia, promoción y otras actividades de mercadotecnia para uno o más productos Hospitalarios. | K169: Gerente Grupo productos - Hospital / Especialidades | L169: Profesional | M169: Especializada (7 a 9 años) | N169: Dominarlo
A170: FQCF41 | B170: GERENTE PRODUCTO JR. LÍNEA ÉTICA | C170: FQCF41 | D170: 21 | E170: QUÍMICO Y FARMA | F170: COMERCIAL FARMA | G170: Farmacéutica | H170: 4 | I170: GERENTES | J170: Responsable de la planeación, coordinación y definición de los objetivos de venta, estrategias de mercadotecnia, análisis de rentabilidad, potencial de mercado, competencia, promoción y otras actividades de mercadotecnia para un o mas productos Éticos. | K170: Gerente grupo de productos línea ética | L170: Profesional | M170: Especializada (7 a 9 años) | N170: Dominarlo
A171: FQGC40 | B171: DIRECTOR TÉCNICO | C171: FQGC40 | D171: 21 | E171: QUÍMICO Y FARMA | F171: GARANTIA Y CONTROL DE CALIDAD | G171: FARMA | H171: 4 | I171: GERENTES | J171: Responderá por el control y registro de marcas, tramites ante el invita y entes regulatorios, realizar estudios de viabilidad estudios nuevos, liberación de materias primas, material de empaque, producto terminado y auditoria a terceros. | K171: Gerente médico Grupo d productos | L171: Profesional | M171: Especializada (7 a 9 años) | N171: Dominarlo
A172: FQDI40 | B172: GERENTE DIAGNOSTICA | C172: FQDI40 | D172: 21 | E172: QUÍMICO Y FARMA | F172: DIAGNOSTICA | G172: FARMA | H172: 4 | I172: GERENTES | J172: Químico Farmacéutico con experiencia mínima de 3 años en cargos similares en el área de Investigación y Desarrollo en Laboratorios farmacéuticos, responde por el desarrollo y formulación de nuevos productos en las líneas farma y químico, elaboración de documentación e información técnica, estudios de estabilidad, desarrollo y validación de técnicas analíticas y de diagnostico, desarrollo de lotes pilotos y procedimientos de manufactura, manejo de equipos de análisis de laboratorio. | K172: Gerente general / Presidente | L172: Profesional | M172: Especializada (7 a 9 años) | N172: Dominarlo
A173: FQCF40 | B173: GERENTE DIVISIÓN FARMA | C173: FQCF40 | D173: 21 | E173: QUÍMICO Y FARMA | F173: COMERCIAL FARMA | G173: FARMA | H173: 4 | I173: GERENTES | J173: Participa en la definición de políticas de comercialización de los productos como el diseño de la estrategia comercial a seguir, con el ánimo de garantizar la venta de los productos y servicios de la compañía; el cargo requiere un Administrador o profesional en carreras afines y conocimientos sólidos en mercadeo y un mínimo de 5 años de experiencia. | K173: Gerente Comercial | L173: Profesional | M173: Especializada (7 a 9 años) | N173: Dominarlo
A174: FQCH40 | B174: GERENTE DIVISIÓN HOSPITALARIA | C174: FQCH40 | D174: 21 | E174: QUÍMICO Y FARMA | F174: HOSPITALARIA | G174: FARMA | H174: 4 | I174: GERENTES | J174: Participa en la definición de políticas de comercialización de los productos como el diseño de la estrategia comercial a seguir, con el ánimo de garantizar la venta de los productos y servicios de la compañía; el cargo requiere un Administrador o profesional en carreras afines y conocimientos sólidos en mercadeo y un mínimo de 5 años de experiencia. | K174: Gerente Grupo productos - Hospital / Especialidades | L174: Profesional | M174: Especializada (7 a 9 años) | N174: Dominarlo
A175: FQNT40 | B175: GERENTE DIVISIÓN NUTRICIÓN | C175: FQNT40 | D175: 21 | E175: QUÍMICO Y FARMA | F175: NUTRICION | G175: FARMA | H175: 4 | I175: GERENTES | J175: Participa en la definición de políticas de comercialización de los productos como el diseño de la estrategia comercial a seguir, con el ánimo de garantizar la venta de los productos y servicios de la compañía; el cargo requiere un Administrador o profesional en carreras afines y conocimientos sólidos en mercadeo y un mínimo de 5 años de experiencia. | K175: Gerente general / Presidente | L175: Profesional | M175: Especializada (7 a 9 años) | N175: Dominarlo
A176: GHED40 | B176: GERENTE CAPACITACIÓN Y DESARROLLO | C176: GHED40 | D176: 6 | E176: GESTIÓN HUMANA | F176: ENTRENAMIENTO Y DESARROLLO | G176: ENTRENAMIENTO Y DESARROLLO | H176: 4 | I176: GERENTES | J176: Otros Nombres: Gerente Desarrollo de Personal, Gerente Desarrollo Organizacional. Responsable por desarrollar programas sobre clima organizacional, evaluación de desempeño, capacitación y entrenamiento para el desarrollo del personal de la compañía; este cargo es desempeñado por Psicólogos, Administradores de Empresas, Ingenieros Industriales, con experiencia superior a 10 años. Reporta a: Vicepresidente de Gestión Humana | K176: Vicepresidente de Gestion humana | L176: Profesional | M176: Especializada (7 a 9 años) | N176: Dominarlo
A177: LSTD40 | B177: GERENTE DISTRIBUCIÓN | C177: LSTD40 | D177: 10 | E177: LOGÍSTICA Y SUMINISTROS | F177: TRANSPORTE Y DISTRIBUCION | G177: DESPACHOS | H177: 4 | I177: GERENTES | J177: Maneja las actividades de distribución, que comprenden la recepción, expedición, control de inventarios y distribución, con el objetivo de satisfacer las necesidades de clientes internos y externos dentro de términos y costos compatibles. Planea y atiende las necesidades de espacio y almacenamiento, evalúa la eficiencia de los medios de transporte y propone mejoras para poder optimizar el proceso de distribución. Requiere de una experiencia entre 10 años y el dominio de un segundo idioma. Reporta a: Vicepresidente de Logística y Operaciones, Gerente General. | K177: Vicepresidente de Logística y Operaciones / Gerente General. | L177: Profesional | M177: Especializada (7 a 9 años) | N177: Dominarlo
... A210: SGAT40 | B210: GERENTE TÉCNICO ACTUARIAL | C210: SGAT40 | D210: 22 | E210: SERVICIOS FINANCIEROS Y SEGUROS | F210: ACTUARIA | G210: Actuarial | H210: 4 | I210: GERENTES | J210: Responsable por la estrategia de formulación metodológica de los cálculos actuariales, para el análisis global de las diferentes carteras de la compañía, buscando minimizar los riesgos involucrados, tanto de volúmenes como de valores. | K210: Gerente Financiero | L210: Profesional | M210: Especializada (7 a 9 años) | N210: Dominarlo
A211: ATAT48 | B211: DIRECTOR DESARROLLO | C211: ATAT48 | D211: 16 | E211: ALTA TECNOLOGÍA Y TELECOMUNICACIONES | F211: 0 | G211: 0 | H211: 4 | I211: GERENTES | J211: Aprobar y diseñar las nuevas estructuras de microondas, se encarga de la verificación y coordinación de procesos de construcción, licitación de obras civiles y dotación de lugares de operación. | K211: Vicepresidente / Gerente técnico | L211: Especialización | M211: Especializada (7 a 9 años) | N211: Dominarlo
A212: MCCM40 | B212: DIRECTOR MEDIO COMUNICACIÓN | C212: MCCM40 | D212: 25 | E212: MEDIOS | F212: COMUNICACON | G212: 0 | H212: 4 | I212: GERENTES | J212: Tomar las decisiones sobre el tiempo de información que debe salir en el medio que dirige, teniendo en cuenta las políticas ideológicas de la junta directiva. Es quien dirige la ideología del medio de comunicación y asegura por medio de sus directores de área que el enfoque de la información esté acorde con los lineamientos organizacionales. | K212: Junta directiva | L212: Profesional | M212: Especializada (7 a 9 años) | N212: Dominarlo
A213: ATAT41 | B213: DIRECTOR NACIONAL CENTROS SERVICIO | C213: ATAT41 | D213: 16 | E213: ALTA TECNOLOGÍA Y TELECOMUNICACIONES | F213: 0 | G213: 0 | H213: 4 | I213: GERENTES | J213: Mantener los centros de ventas y servicios al cliente, mejorando los procesos de atención. Atender clientes, responder por la caja, prestar servicio técnico y controlar inventario asignado, orientando su labor hacia la mejora en la calidad. | K213: Vicepresidente / Gerente servicio al cliente | L213: Profesional | M213: Especializada (7 a 9 años) | N213: Dominarlo
A214: ATAT42 | B214: DIRECTOR NACIONAL SERVICIOS | C214: ATAT42 | D214: 16 | E214: ALTA TECNOLOGÍA Y TELECOMUNICACIONES | F214: 0 | G214: 0 | H214: 4 | I214: GERENTES | J214: Realiza el proceso de retención de clientes, créditos, legalizaciones, activaciones brindando a los usuarios una respuesta rápida y oportuna. | K214: Gerente general | L214: Profesional | M214: Especializada (7 a 9 años) | N214: Dominarlo
A215: ATAT43 | B215: DIRECTOR OPERACIONES (TELECOMUNICACIONES) | C215: ATAT43 | D215: 16 | E215: ALTA TECNOLOGÍA Y TELECOMUNICACIONES | F215: 0 | G215: 0 | H215: 4 | I215: GERENTES | J215: Responsable por el mantenimiento preventivo y correctivo a nivel de las estaciones celulares, coordinar contratos de estaciones y mantenimiento de red. | K215: Vicepresidente / Gerente técnico | L215: Profesional | M215: Especializada (7 a 9 años) | N215: Dominarlo
A216: ATAT44 | B216: DIRECTOR PLANEACION TECNICA | C216: ATAT44 | D216: 16 | E216: ALTA TECNOLOGÍA Y TELECOMUNICACIONES | F216: 0 | G216: 0 | H216: 4 | I216: GERENTES | J216: Planear a largo plazo el área técnica, administrar los datos de switch, generar planes a corto, mediano y largo plazo para el adecuado funcionamiento de la red Nacional. Responder por la investigación y desarrollo de nuevas tecnologías. | K216: Vicepresidente / Gerente técnico | L216: Profesional | M216: Especializada (7 a 9 años) | N216: Dominarlo
A217: ATAT49 | B217: DIRECTOR TERMINALES CELULARES | C217: ATAT49 | D217: 16 | E217: ALTA TECNOLOGÍA Y TELECOMUNICACIONES | F217: 0 | G217: 0 | H217: 4 | I217: GERENTES | J217: Controlar los equipos celulares, atención postventa, administrar el convenio de teléfonos celulares y desarrollo de productos. Realizar la evaluación técnica de los celulares antes de la venta. | K217: Vicepresidente / Gerente de Servicio al Cliente. | L217: Profesional | M217: Especializada (7 a 9 años) | N217: Dominarlo
A218: ATAT45 | B218: DIRECTOR TRANSMISIONES | C218: ATAT45 | D218: 16 | E218: ALTA TECNOLOGÍA Y TELECOMUNICACIONES | F218: 0 | G218: 0 | H218: 4 | I218: GERENTES | J218: Planear, supervisar y mantener en perfecto funcionamiento el sistema de microondas, establecer planes de contingencia y velar por un mantenimiento que permita la operación óptima del equipo. | K218: Vicepresidente / Gerente técnico | L218: Profesional | M218: Especializada (7 a 9 años) | N218: Dominarlo
A219: ATAT40 | B219: GERENTE ESTADISTICAS E INFORMACION | C219: ATAT40 | D219: 16 | E219: ALTA TECNOLOGÍA Y TELECOMUNICACIONES | F219: 0 | G219: 0 | H219: 4 | I219: GERENTES | J219: Desarrolla y ejecuta los procesos de recopilación y procesamiento de la información técnica y financiera requerida por la vicepresidencia técnica. | K219: Gerente general / Presidente | L219: Profesional | M219: Especializada (7 a 9 años) | N219: Dominarlo
A220: ATAT46 | B220: GERENTE FRAUDES | C220: ATAT46 | D220: 16 | E220: ALTA TECNOLOGÍA Y TELECOMUNICACIONES | F220: 0 | G220: 0 | H220: 4 | I220: GERENTES | J220: Apoya al director de fraudes en todo lo relacionado en la detección y control de fraudes en la compañía y en la determinación de la tecnología que se necesita en el manejo de estas situaciones. | K220: Gerente general / Presidente | L220: Profesional | M220: Especializada (7 a 9 años) | N220: Dominarlo
A221: SGID40 | B221: GERENTE INDEMNIZACION | C221: SGID40 | D221: 22 | E221: SERVICIOS FINANCIEROS Y SEGUROS | F221: INDEMNIZACIONES | G221: 0 | H221: 4 | I221: GERENTES | J221: Asegurar la excelencia del servicio en la atención de reclamos, verificando que este se realice bajo el cumplimiento de normas legales y políticas de la compañía, mediante la planeación, organización y dirección en la gestión. Determinar que los reclamos se realicen bajo las políticas y normas legales mediante la planeación, orientación y control de la gestión en la sucursal. | K221: Presidente / vicepresidente | L221: Profesional | M221: Especializada (7 a 9 años) | N221: Dominarlo
A222: ATAT47 | B222: GERENTE OPERACIONES TELECOMUNICACIONES | C222: ATAT47 | D222: 16 | E222: ALTA TECNOLOGÍA Y TELECOMUNICACIONES | F222: 0 | G222: 0 | H222: 4 | I222: GERENTES | J222: Responder por el funcionamiento adecuado de las operaciones técnicas a nivel nacional; la activación de tele puertos, mantenimiento de telecomunicaciones, control de gestión de instalación, seguimiento y montaje de los equipos. | K222: Gerente general / Presidente | L222: Profesional | M222: Especializada (7 a 9 años) | N222: Dominarlo
A223: SGRE41 | B223: GERENTE REASEGUROS | C223: SGRE41 | D223: 22 | E223: SERVICIOS FINANCIEROS Y SEGUROS | F223: REASEGUROS | G223: 0 | H223: 4 | I223: GERENTES | J223: Coordinar y dirigir los procesos de reaseguros, manteniendo comunicación con empresas especializadas y compañías de seguros, tanto a nivel nacional como internacional y asegurar que los pagos se efectúen apropiadamente. | K223: Presidente / Gerente general | L223: Profesional | M223: Especializada (7 a 9 años) | N223: Dominarlo
A224: SGSC40 | B224: GERENTE SUSCRIPCION | C224: SGSC40 | D224: 22 | E224: SERVICIOS FINANCIEROS Y SEGUROS | F224: SUSCRIPCION | G224: 0 | H224: 4 | I224: GERENTES | J224: Planear, coordinar y controlar las suscripciones así como el mantenimiento y desarrollo de negocios rentables, cumpliendo con los estándares de suscripción y servicios establecidos previamente por la compañía. | K224: Vicepresidente suscripción | L224: Profesional | M224: Especializada (7 a 9 años) | N224: Dominarlo
A225: CTAD40 | B225: GERENTE TÉCNICO - CONSTRUCCIONES | C225: CTAD40 | D225: 18 | E225: CONSTRUCCIÓN E INSUMOS | F225: ADMINISTRATIVA | G225: 0 | H225: 4 | I225: GERENTES | J225: Gerenciar los procesos técnicos de construcción de las obras, para que se enmarquen dentro de las especificaciones de calidad y de diseño de los proyectos, manteniendo controlados los costos y el cronograma de entrega. | K225: Gerente general / Presidente | L225: Profesional | M225: De 4 a 6 años | N225: No requiere
A226: MCCM41 | B226: SUBDIRECTOR MEDIO COMUNICACIÓN | C226: MCCM41 | D226: 25 | E226: MEDIOS | F226: COMUNICACON | G226: 0 | H226: 4 | I226: GERENTES | J226: En conjunto con el director maneja la información de acuerdo con las políticas e ideologías del medio. Tiene a su cargo los directores de sección o de área y determina la manera como se manejan temas específicos. | K226: Gerente general | L226: Profesional | M226: Especializada (7 a 9 años) | N226: Dominarlo
A227: COVS50 | B227: DIRECTOR / JEFE COMERCIAL | C227: COVS50 | D227: 3 | E227: COMERCIAL | F227: VENTAS | G227: VENTAS | H227: 5 | I227: JEFES | J227: Dirigir, Coordinar y hacer cumplir las políticas y procedimientos, relacionados con el mercadeo y ventas de los productos y / o servicios ofrecidos por la compañía. | K227: Presidente o gerente general | L227: Profesional | M227: De 5 a 7 años | N227: Básico
A228: COVS51 | B228: GERENTE COMERCIAL ZONA | C228: COVS51 | D228: 3 | E228: COMERCIAL | F228: VENTAS | G228: VENTAS | H228: 5 | I228: JEFES | J228: Coordinar y supervisar el desarrollo de las actividades comerciales de un grupo de oficinas. Es el responsable de la programación de los productos y servicios por medio de una permanente orientación comercial que refuerce su posición en el mercado. | K228: Gerente de zona | L228: Profesional | M228: Dos puestos previos (4 a 6 años) | N228: Básico
A229: COVS52 | B229: GERENTE DISTRITO O SUCURSAL | C229: COVS52 | D229: 3 | E229: COMERCIAL | F229: VENTAS | G229: VENTAS | H229: 5 | I229: JEFES | J229: Responder por la venta y distribución de los productos o servicios que le han sido recomendados. Tener a cargo una sucursal o distrito para administrar la oficina, controlar la bodega local y dirigir los vendedores de su distrito. | K229: Gerente de ventas / Gerente comercial | L229: Profesional | M229: Dos puestos previos (4 a 6 años) | N229: Básico
A230: FNOP51 | B230: JEFE DEPARTAMENTO EXTRANJERO | C230: FNOP51 | D230: 22 | E230: SERVICIOS FINANCIEROS Y SEGUROS | F230: OPERACIONES | G230: TESORERIA | H230: 5 | I230: JEFES | J230: Dirige y controla todas las operaciones que se realizan en el departamento, además de prestar asesoría en los negocios de comercio exterior a los clientes. Atiende a clientes que soliciten los servicios del banco para sus negocios con el exterior; diligencia solicitudes de cartas de crédito sobre exterior; diligencia reintegros por exportación. Controla y gestiona los vencimientos de clientes, registra las operaciones contables en moneda extranjera. | K230: Gerente Financiero | L230: Profesional | M230: Dos puestos previos (4 a 6 años) | N230: Comunicarse
A231: FNTM50 | B231: JEFE MESA DINERO | C231: FNTM50 | D231: 22 | E231: SERVICIOS FINANCIEROS Y SEGUROS | F231: TESORERIA MESA | G231: TESORERIA | H231: 5 | I231: JEFES | J231: Planea, controla y dirige las actividades relacionadas con la compra y venta de dinero dentro del mercado financiero. Coordina la elaboración de presupuestos o proyecciones de flujos de efectivo de la entidad, las operaciones de compra y venta en moneda local y extranjera. Administra los riesgos que se generan al buscar utilidades bajos las normas legales vigentes. Se requiere un profesional del área financiera con una experiencia de 3 a 5 años en cargos similares. | K231: Gerente Financiero / Vicepresidente Financiero | L231: Profesional | M231: Dos puestos previos (4 a 6 años) | N231: Comunicarse
A232: FNFD50 | B232: JEFE SECCIÓN FIDUCIARIA | C232: FNFD50 | D232: 22 | E232: SERVICIOS FINANCIEROS Y SEGUROS | F232: FIDUCIARIA | G232: TESORERIA | H232: 5 | I232: JEFES | J232: Controla las inversiones del banco y constituye y cancela valores en custodia y garantía; además, coordina y supervisa las actividades realizadas por su personal; entrega títulos valores. Mantiene comunicaciones con la Bolsa para averiguar cotizaciones de diferentes papeles. Revisa las contabilizaciones hechas por los auxiliares del departamento. Realiza el cuadre contable de las operaciones efectuadas en el día. | K232: Gerente producto negocio fiduciario | L232: Profesional | M232: Dos puestos previos (4 a 6 años) | N232: Básico
A233: FITS50 | B233: JEFE TESORERIA | C233: FITS50 | D233: 5 | E233: FINANCIERA | F233: TESORERIA | G233: TESORERIA | H233: 5 | I233: JEFES | J233: Ejecutar y manejar los fondos de la organización, efectuar colocaciones, proyectar flujos, garantizar la calidad de la información financiera que resulta de las operaciones que se llevan a cabo en Tesorería y buscar las mejores opciones en rentabilidad para la compañía. | K233: Gerente tesorería / Gerente financiero | L233: Profesional | M233: Dos puestos previos (4 a 6 años) | N233: Comunicarse
A234: COSC53 | B234: JEFE TELEMARKETING - ACTIVO | C234: COSC53 | D234: 3 | E234: COMERCIAL | F234: SERVICIO AL CLIENTE | G234: TELEMARKETING | H234: 5 | I234: JEFES | J234: Coordina los procesos de telemarketing activo, buscando conseguir nuevos clientes, de acuerdo con la política comercial preestablecida. Desarrolla el equipo de operadores, buscando capacitarlos para dar una correcta atención al cliente, así como para optimizar la política de expansión y conquista de nuevos clientes y el grado del relación cliente-empresa. | K234: Gerente Telemarketing | L234: Profesional | M234: Dos puestos previos (4 a 6 años) | N234: Comunicarse
...

Sheet HOMOLOGACIÓN
C2: Cargo Valorado | D2: Cargo Homologado 1 | E2: Descripción 1 | F2: Cargo Homologado 2 | G2: Descripción 2 | H2: Observaciones
E3: =IFERROR(VLOOKUP(Tabla1[[#This Row],[Cargo Homologado 1]],'[1]catalogo '!$b$1:$J$1052,9,0)," ") | G3: =IFERROR(VLOOKUP(Tabla1[[#This Row],[Cargo Homologado 2]],'[1]catalogo '!$b$1:$J$1052,9,0)," ")
E4: =IFERROR(VLOOKUP(Tabla1[[#This Row],[Cargo Homologado 1]],'[1]catalogo '!$b$1:$J$1052,9,0)," ") | G4: =IFERROR(VLOOKUP(Tabla1[[#This Row],[Cargo Homologado 2]],'[1]catalogo '!$b$1:$J$1052,9,0)," ")

Sheet Plantilla de Homologación
D1: {=INDIRECT(VLOOKUP(#ref!,CATALOGO!$AE$3:$AG$29,3,0))} -> #NAME? | E1: =IFERROR(VLOOKUP(F3,CATALOGO!$AJ$2:$AM$27,4,0),"") -> Vicepresidente / Director Región / Presidente País
B2: NOMBRE CARGO | C2: AREA EMPRESA | D2: CARGO HOMOLOGADO | E2: PISTA | F2: CAT
E3: =IFERROR(VLOOKUP(F3,CATALOGO!$AJ$2:$AM$27,4,0),"") -> Vicepresidente / Director Región / Presidente País | F3: 20
E4: =IFERROR(VLOOKUP(F4,CATALOGO!$AJ$2:$AM$27,4,0),"") -> Gerente / Gerente Región / Gerente País / Gerente Unidad de Negocio / Gerente de Cuenta | F4: 18
E5: =IFERROR(VLOOKUP(F5,CATALOGO!$AJ$2:$AM$27,4,0),"") -> Gerente / Gerente Región / Gerente País / Gerente Unidad de Negocio / Gerente de Cuenta | F5: 18
E6: =IFERROR(VLOOKUP(F6,CATALOGO!$AJ$2:$AM$27,4,0),"") -> Gerente / Gerente Región / Gerente País / Gerente Unidad de Negocio / Gerente de Cuenta | F6: 16
E7: =IFERROR(VLOOKUP(F7,CATALOGO!$AJ$2:$AM$27,4,0),"") -> Director / Jefe / Especialista Sr / Ingeniero / Ejecutivo de Cuenta | F7: 15
E8: =IFERROR(VLOOKUP(F8,CATALOGO!$AJ$2:$AM$27,4,0),"") -> Director / Jefe / Especialista Sr / Ingeniero / Ejecutivo de Cuenta | F8: 15
E9: =IFERROR(VLOOKUP(F9,CATALOGO!$AJ$2:$AM$27,4,0),"") -> Director / Jefe / Especialista Sr / Ingeniero / Ejecutivo de Cuenta | F9: 15
E10: =IFERROR(VLOOKUP(F10,CATALOGO!$AJ$2:$AM$27,4,0),"") -> Director / Jefe / Especialista Sr / Ingeniero / Ejecutivo de Cuenta | F10: 15
E11: =IFERROR(VLOOKUP(F11,CATALOGO!$AJ$2:$AM$27,4,0),"") -> Director / Jefe / Especialista Sr / Ingeniero / Ejecutivo de Cuenta | F11: 15
E12: =IFERROR(VLOOKUP(F12,CATALOGO!$AJ$2:$AM$27,4,0),"") -> Director / Jefe / Especialista Sr / Ingeniero / Ejecutivo de Cuenta | F12: 15
E13: =IFERROR(VLOOKUP(F13,CATALOGO!$AJ$2:$AM$27,4,0),"") -> Director / Jefe / Especialista Sr / Ingeniero / Ejecutivo de Cuenta | F13: 15
E14: =IFERROR(VLOOKUP(F14,CATALOGO!$AJ$2:$AM$27,4,0),"") -> Director / Jefe / Especialista Sr / Ingeniero / Ejecutivo de Cuenta | F14: 14
... E83: =IFERROR(VLOOKUP(F83,CATALOGO!$AJ$2:$AM$27,4,0),"") -> Auxiliar / Operario II / Representante de Ventas Sr | F83: 4
E84: =IFERROR(VLOOKUP(F84,CATALOGO!$AJ$2:$AM$27,4,0),"")
E85: =IFERROR(VLOOKUP(F85,CATALOGO!$AJ$2:$AM$27,4,0),"")
E86: =IFERROR(VLOOKUP(F86,CATALOGO!$AJ$2:$AM$27,4,0),"")
E87: =IFERROR(VLOOKUP(F87,CATALOGO!$AJ$2:$AM$27,4,0),"")
E88: =IFERROR(VLOOKUP(F88,CATALOGO!$AJ$2:$AM$27,4,0),"")
E89: =IFERROR(VLOOKUP(F89,CATALOGO!$AJ$2:$AM$27,4,0),"")
E90: =IFERROR(VLOOKUP(F90,CATALOGO!$AJ$2:$AM$27,4,0),"")
E91: =IFERROR(VLOOKUP(F91,CATALOGO!$AJ$2:$AM$27,4,0),"")
E92: =IFERROR(VLOOKUP(F92,CATALOGO!$AJ$2:$AM$27,4,0),"")
E93: =IFERROR(VLOOKUP(F93,CATALOGO!$AJ$2:$AM$27,4,0),"")
E94: =IFERROR(VLOOKUP(F94,CATALOGO!$AJ$2:$AM$27,4,0),"")
E95: =IFERROR(VLOOKUP(F95,CATALOGO!$AJ$2:$AM$27,4,0),"")
... E98: =IFERROR(VLOOKUP(F98,CATALOGO!$AJ$2:$AM$27,4,0),"")

Sheet LISTA
B3: NOMBRE | C3: NIVEL | D3: AREA GENERAL | E3: NOMBRE
B4: VICEPRESIDENTE ADMINISTRATIVO | C4: 2 | D4: ADMINISTRATIVA | E4: VICEPRESIDENTE ADMINISTRATIVO
B5: GERENTE ADMINISTRATIVO | C5: 3 | D5: ADMINISTRATIVA | E5: GERENTE ADMINISTRATIVO
B6: GERENTE SERVICIOS GENERALES | C6: 4 | D6: ADMINISTRATIVA | E6: GERENTE SERVICIOS GENERALES
B7: GERENTE SEGURIDAD FISICA | C7: 4 | D7: ADMINISTRATIVA | E7: GERENTE SEGURIDAD FISICA
B8: GERENTE PROYECTOS | C8: 4 | D8: ADMINISTRATIVA | E8: GERENTE PROYECTOS
B9: GERENTE ORGANIZACION Y METODOS | C9: 4 | D9: ADMINISTRATIVA | E9: GERENTE ORGANIZACION Y METODOS
B10: GERENTE INFRAESTRUCTURA FISICA | C10: 4 | D10: ADMINISTRATIVA | E10: GERENTE INFRAESTRUCTURA FISICA
B11: GERENTE INMUEBLES | C11: 4 | D11: ADMINISTRATIVA | E11: GERENTE INMUEBLES
B12: JEFE MANTENIMIENTO EDIFICACIONES | C12: 5 | D12: ADMINISTRATIVA | E12: JEFE MANTENIMIENTO EDIFICACIONES
B13: JEFE PROYECTO | C13: 5 | D13: ADMINISTRATIVA | E13: JEFE PROYECTO
B14: JEFE PROCESOS | C14: 5 | D14: ADMINISTRATIVA | E14: JEFE PROCESOS
B15: JEFE ORGANIZACION Y METODOS | C15: 5 | D15: ADMINISTRATIVA | E15: JEFE ORGANIZACION Y METODOS
... B1053: ANALISTA DESARROLLO REDES | C1053: 7 | D1053: VEHÍCULOS Y PARTES | E1053: ANALISTA DESARROLLO REDES

Sheet CATALOGO
B2: ADMINISTRATIVA | C2: AGROINDUSTRIA Y PECUARIO | D2: ALTA TECNOLOGÍA Y TELECOMUNICACIONES | E2: AUDITORIA | F2: COMERCIAL | G2: CONSTRUCCIÓN E INSUMOS | H2: CONSUMO MASIVO | I2: CORPORATIVO | J2: FINANCIERA | K2: GESTIÓN HUMANA | L2: HOTELERIA TURISMO Y RECREACIÓN | M2: I & D | N2: JURÍDICA | O2: LOGÍSTICA Y SUMINISTROS | P2: MANUFACTURA E INDUSTRIA | Q2: MEDIOS | R2: MERCADEO | S2: MINERIA, ENERGIA E HIDROCARBUROS | T2: OPERACIONES | U2: OPERARIOS | V2: QUÍMICO Y FARMA | W2: SERVICIOS DE SALUD | X2: SERVICIOS EDUCATIVOS | Y2: SERVICIOS FINANCIEROS Y SEGUROS | Z2: TECNOLOGÍA E INFORMÁTICA | AA2: TEXTILES CONFECCIONES Y CALZADO | AB2: VEHÍCULOS Y PARTES | AJ2: CATEGORIA | AK2: RUTA CARRERA GERENCIAL | AL2: RUTA CARRERA CONTRIBUCION INDIVIDUAL | AM2: PISTA
B3: VICEPRESIDENTE ADMINISTRATIVO | C3: GERENTE CULTIVO | D3: VICEPRESIDENTE CONSULTORÍA TI | E3: VICEPRESIDENTE CONTRALOR | F3: VICEPRESIDENTE COMERCIAL | G3: GERENTE CONSTRUCCIONES | H3: VICEPRESIDENTE CATEGORÍA | I3: PRESIDENTE - REGIONAL | J3: VICEPRESIDENTE GERENCIAMENTO RIESGO | K3: VICEPRESIDENTE GESTION HUMANA | L3: JEFE RESERVAS Y/O HABITACIONES | M3: GERENTE DESARROLLO PRODUCTOS | N3: VICEPRESIDENTE JURIDICO | O3: VICEPRESIDENTE INTERNACIONAL | P3: VICEPRESIDENTE MANUFACTURA | Q3: DIRECTOR MEDIO COMUNICACIÓN | R3: VICEPRESIDENTE MERCADEO | S3: GERENTE PERFORACION | T3: VICEPRESIDENTE OPERACIONES | U3: CONDUCTOR VEHÍCULO PESADO | V3: VICEPRESIDENTE INVESTIGACIÓN CLÍNICA | W3: DIRECTOR CIENTÍFICO (CLÍNICA U HOSPITAL) | X3: RECTOR | Y3: VICEPRESIDENTE SINIESTROS | Z3: VICEPRESIDENTE SISTEMAS | AA3: JEFE DISEÑO | AB3: GERENTE DESARROLLO REDES | AE3: ADMINISTRATIVA | AF3: B | AG3: ="CATALOGO!$"&AF3&"$3:$"&AF3&"$155" -> CATALOGO!$B$3:$B$155 | AJ3: 25 | AK3: Presidente Global | AM3: =IF(AK3="","",AK3)&IF(OR(AL3="",AK3=""),""," / ")&AL3 -> Presidente Global
B4: GERENTE ADMINISTRATIVO | C4: AGRONOMO | D4: VICEPRESIDENTE VENTAS ALTA TECNOLOGÍA (GENÉRICO) | E4: GERENTE AUDITORIA INTERNA | F4: VICEPRESIDENTE SERVICIOS AL CLIENTE | G4: DIRECTOR PROYECTO | H4: GERENTE CATEGORÍA | I4: GERENTE GENERAL | J4: DIRETOR RELACIONES CON INVERSIONISTAS | K4: GERENTE RECLUTAMIENTO Y SELECCIÓN | L4: GERENTE ALIMENTOS Y BEBIDAS | M4: GERENTE INVESTIGACIÓN Y DESARROLLO | N4: GERENTE JURÍDICO CORPORATIVO | O4: VICEPRESIDENTE LOGÍSTICA | P4: VICEPRESIDENTE MANUFACTURA | Q4: SUBDIRECTOR MEDIO COMUNICACIÓN | R4: GERENTE MERCADEO | S4: GERENTE INGENIERIA | T4: GERENTE OPERACIONES | U4: TÉCNICO MECÁNICO II | V4: VICEPRESIDENTE MEDICO | W4: DIRECTOR MEDICO SERVICIOS SALUD | X4: VICERECTOR ACADEMICO | Y4: VICEPRESIDENTE UNIDAD NEGOCIO - GENERALES | Z4: GTE INFRAESTRUCTURA | AA4: DISEÑADORA MODAS | AB4: GERENTE SERVICIOS/GARANTÍA | AE4: AGROINDUSTRIA Y PECUARIO | AF4: C | AG4: ="CATALOGO!$"&AF4&"$3:$"&AF4&"$155" -> CATALOGO!$C$3:$C$155 | AJ4: 24 | AK4: Presidente Regional | AM4: =IF(AK4="","",AK4)&IF(OR(AL4="",AK4=""),""," / ")&AL4 -> Presidente Regional
B5: GERENTE SERVICIOS GENERALES | C5: JEFE POSTCOSECHA | D5: VICEPRESIDENTE TECNICO TELECOMINICACIONES | E5: JEFE CUMPLIMIENTO | F5: GERENTE UNIDAD NEGOCIO | G5: DIRECTOR DISEÑO | H5: GERENTE TRADE MKARKETING | I5: PRESIDENTE PAIS | J5: VICEPRESIDENTE FINANCIERO | K5: GERENTE GESTION HUMANA | L5: JEFE MANTENIMIENTO (SERVICIOS) | M5: GERENTE DESARROLLO EMPAQUES | N5: SECRETARIO GENERAL | O5: GERENTE NEGOCIOS INTERNACIONALES | P5: VICEPRESIDENTE INDUSTRIAL | Q5: JEFE REDACCION | R5: GTE CANALES ALTERNATIVOS | S5: GERENTE PROYECTOS - HIDROCARBUROS | T5: JEFE /COORDINADOR OPERACIONES | U5: OPERADOR MAQUINARIA ESPECIALIZADA | V5: GERENTE GRUPO PRODUCTOS - HOSPITAL /ESPECIALIDADES | W5: MEDICO SUB ESPECIALISTA | X5: DIRECTOR POSTGRADO | Y5: VICEPRESIDENTE COMERCIAL CANAL RETAIL | Z5: GERENTE SISTEMAS | AA5: COORDINADOR DE CORTE | AB5: JEFE ./COORDINADOR/ESP. DESARROLLO REDES | AE5: ALTA TECNOLOGÍA Y TELECOMUNICACIONES | AF5: D | AG5: ="CATALOGO!$"&AF5&"$3:$"&AF5&"$155" -> CATALOGO!$D$3:$D$155 | AJ5: 23 | AK5: Presidente Pais | AM5: =IF(AK5="","",AK5)&IF(OR(AL5="",AK5=""),""," / ")&AL5 -> Presidente Pais
B6: GERENTE SEGURIDAD FISICA | C6: ADMINISTRADOR GRANJAS | D6: CONSULTOR CONTRATOS, LICIT. Y PROPUESTAS - ESPEC./S | E6: JEFE AUDITORIA INTERNA | F6: VICEPRESIDENTE DESARROLLO NEGOCIOS | G6: GERENTE TÉCNICO - CONSTRUCCIONES | H6: JEFE CATEGORÍA | I6: PRESIDENTE/ GERENTE GENERAL - PAIS | J6: VICEPRESIDENTE CREDITO | K6: GERENTE RELACIONES LABORALES/SINDICALES | L6: JEFE ALIMENTOS Y BEBIDAS | M6: JEFE INVESTIGACION Y DESARROLLO | N6: GERENTE JURIDICO | O6: GERENTE OPERACIONES INTERNACIONALES | P6: VICEPRESIDENTE TÉCNICO | Q6: COORDINADOR COPRODUCCION Y ALIANZAS CONTENIDO | R6: GERENTE PUBLICIDAD | S6: DIRECTOR HSEQ | T6: ANALISTA OPERACIONES | U6: OPERARIO MONTACARGA | V6: GERENTE MEDICO GRUPO PRODUCTOS | W6: AUDITOR ODONTOLOGIA / MEDICO | X6: RECTOR COLEGIO | Y6: VICEPRESIDENTE SINIESTROS ARP | Z6: GERENTE OPERACIÓN SISTEMAS | AA6: PATRONISTA | AB6: COORDINADOR/JEFESERVICIOS/GARANTÍA | AE6: AUDITORIA | AF6: E | AG6: ="CATALOGO!$"&AF6&"$3:$"&AF6&"$155" -> CATALOGO!$E$3:$E$155 | AJ6: 22 | AK6: Vicepresidente / Director Región / Presidente País | AM6: =IF(AK6="","",AK6)&IF(OR(AL6="",AK6=""),""," / ")&AL6 -> Vicepresidente / Director Región / Presidente País
B7: GERENTE PROYECTOS | C7: DIRECTOR INCUBACIÓN | D7: DIRECTOR DESARROLLO | E7: AUDITOR | F7: VICEPRESIDENTE SERVICIO AL CLIENTE | G7: DIRECTOR OBRA | H7: COORDINADOR PROMOCIÓN Y MERCHANDISING | I7: VICEPRESIDENTE EJECUTIVO | J7: GERENTE ADMINISTRATIVO Y FINANCIERO | K7: GERENTE CAPACITACIÓN Y DESARROLLO | L7: JEFE BANQUETES | M7: DIBUJANTE TÉCNICO PL. | N7: CONSULTOR/COORDINADOR/ESPEC. JURÍDICO | O7: GERENTE REGULATORIO | P7: GERENTE TÉCNICO | Q7: ANALISTA CONTENIDOS | R7: DIRECTOR DE LÍNEA O MARCA | S7: JEFE CONSTRUCCIONES Y OBRAS CIVILES | T7: ASISTENTE OPERACIONES | U7: PINTOR | V7: GERENTE FARMACOVIGILÂNCIA | W7: CIRUJANO ESPECIALIZADO | X7: DIRECTOR INVESTIGACIÓN | Y7: VICEPRESIDENTE SUSCRIPCIÓN | Z7: GERENTE HELPDESK | AA7: AUXILIAR CORTE | AB7: ANALISTA GARANTÍA | AE7: COMERCIAL | AF7: F | AG7: ="CATALOGO!$"&AF7&"$3:$"&AF7&"$155" -> CATALOGO!$F$3:$F$155 | AJ7: 21 | AK7: Vicepresidente / Director Región / Presidente País | AM7: =IF(AK7="","",AK7)&IF(OR(AL7="",AK7=""),""," / ")&AL7 -> Vicepresidente / Director Región / Presidente País
B8: GERENTE ORGANIZACION Y METODOS | C8: DIRECTOR POLLO ENGORDE | D8: DIRECTOR NACIONAL CENTROS SERVICIO | E8: AUDITOR SISTEMAS | F8: GERENTE COMERCIAL | G8: DIRECTOR OBRA - INTERVENTOR | H8: JEFE CAJEROS VENTAS | I8: VICEPRESIDENTE PLANEACION ESTRATÉGICA | J8: GERENTE RIESGOS | K8: GERENTE COMUNICACIÓN INTERNA | L8: JEFE LAVANDERÍA | M8: INGENIERO DESARROLLO PRODUCTOS | N8: DIRECTOR JURIDICO | O8: GERENTE DESARROLLO PROVEEDORES | P8: GERENTE PRODUCCION | Q8: EDITOR GRAFICO | R8: GERENTE GRUPO PRODUCTOS | S8: SUPERINTENDENTE CAMPO | U8: PLOMERO | V8: GERENTE GRUPO PRODUCTOS LÍNEA ÉTICA | W8: CIRUJANO GENERAL | X8: DECANO TIPO A | Y8: GTE SR COMERCIAL CANAL RETAIL | Z8: DIRECTOR DETENCION Y PREVENCION FRAUDES | AB8: ANALISTA DESARROLLO REDES | AE8: CONSTRUCCIÓN E INSUMOS | AF8: G | AG8: ="CATALOGO!$"&AF8&"$3:$"&AF8&"$155" -> CATALOGO!$G$3:$G$155 | AJ8: 20 | AK8: Vicepresidente / Director Región / Presidente País | AM8: =IF(AK8="","",AK8)&IF(OR(AL8="",AK8=""),""," / ")&AL8 -> Vicepresidente / Director Región / Presidente País
B9: GERENTE INFRAESTRUCTURA FISICA | C9: DIRECTOR PRODUCCIÓN POLLO | D9: DIRECTOR NACIONAL SERVICIOS | E9: ANALISTA CUMPLIMIENTO | F9: GTE TELEMARKETING | G9: DIRECTOR TRAMITES | H9: JEFE SECCIÓN VENTAS | I9: VICEPRESIDENTE PLANEACION | J9: GERENTE INVERSIONES | K9: GERENTE COMPENSACIÓN | L9: CHEFF EJECUTIVO | M9: INGENIERO DESARROLLO EMPAQUES - ESPECIALISTA | N9: JEFE DIVISION JURIDICA | O9: GERENTE PLANEACION LOGÍSTICA | P9: GERENTE PROCESOS | Q9: EDITOR SECCION | R9: GERENTE PRODUCTO ESPECIALIZADO | S9: SUPERINTENDENTE PRODUCCIÓN | U9: SOLDADOR | V9: DIRECTOR MEDICO COMERCIAL | W9: ENFERMERA JEFE | X9: DIRECTOR ACADEMICO - COLEGIO | Y9: VICEPRESIDENTE SUSCRIPCIÓN | Z9: GERENTE SEGURIDAD SISTEMAS | AE9: CONSUMO MASIVO | AF9: H | AG9: ="CATALOGO!$"&AF9&"$3:$"&AF9&"$155" -> CATALOGO!$H$3:$H$155 | AJ9: 19 | AK9: Gerente / Gerente Región / Gerente País / Gerente Unidad de Negocio | AM9: =IF(AK9="","",AK9)&IF(OR(AL9="",AK9=""),""," / ")&AL9 -> Gerente / Gerente Región / Gerente País / Gerente Unidad de Negocio
B10: GERENTE INMUEBLES | C10: JEFE LEVANTE | D10: DIRECTOR OPERACIONES (TELECOMUNICACIONES) | E10: ASISTENTE AUDITORIA | F10: GERENTE DESARROLLO NEGOCIOS | G10: INGENIERO OBRA | H10: JEFE TRADE MKARKETING | I10: GERENTE GOBIERNO CORPORATIVO | J10: GERENTE FINANCIERO | K10: JEFE SELECCION | L10: GERENTE ALIMENTOS Y BEBIDAS | M10: ANALISTA INVESTIGACION Y DESARROLLO PRODUCTOS | N10: ASESOR LEGAL | O10: GERENTE MATERIALES | P10: GERENTE PLANEACION Y CONTROL PRODUCCIÓN | Q10: PERIODISTA SENIOR | R10: JEFE /COORDINADOR/ESPEC. PUBLICIDAD | S10: INGENIERO PRODUCCION - PETROLEOS | U10: OPERADOR III | V10: GERENTE INVESTIGACIÓN CLÍNICA | W10: JEFE ADMISIONES | X10: DIRECTOR ADMISIONES - EDUCACIÓN | Y10: VICEPRESIDENTE TECNICO INDEMNIZACIONES | Z10: DIRECTOR INGENIERIA E INFRAESTRUCTURA | AE10: CORPORATIVO | AF10: I | AG10: ="CATALOGO!$"&AF10&"$3:$"&AF10&"$155" -> CATALOGO!$I$3:$I$155 | AJ10: 18 | AK10: Gerente / Gerente Región / Gerente País / Gerente Unidad de Negocio | AL10: Gerente de Cuenta | AM10: =IF(AK10="","",AK10)&IF(OR(AL10="",AK10=""),""," / ")&AL10 -> Gerente / Gerente Región / Gerente País / Gerente Unidad de Negocio / Gerente de Cuenta
B11: JEFE MANTENIMIENTO EDIFICACIONES | C11: SUPERVISOR CAMPO | D11: DIRECTOR PLANEACION TECNICA | E11: AUXILIAR CUMPLIMIENTO | F11: GTE CALL CENTER | G11: INGENIERO RESIDENTE | H11: SUPERVISOR PROMOTORES Y MERCADERISTAS | I11: GERENTE PLANEACION | J11: GERENTE CRÉDITO Y COBRANZA | K11: JEFE SALUD OCUPACIONAL | L11: JEFE RECEPCION | M11: DISEÑADOR INDUSTRIAL | N11: ABOGADO | O11: GERENTE CONTROL INVENTARIOS | P11: GERENTE TECNICO | Q11: REDACTOR | R11: JEFE /COORDINADOR/ESPEC. MARKETING | S11: SUPERINTENDENTE CAMPO | U11: TÉCNICO ELECTRICISTA INDUSTRIAL II | V11: GERENTE PRODUCTO - HOSPITAL /ESPECIALIDADES | W11: JEFE ATENCIÓN MÉDICA | X11: DIRECTOR BIBLIOTECA | Y11: GERENTE OPERACIONES BANCARIAS | Z11: GERENTE PROYECTOS SISTEMAS | AE11: FINANCIERA | AF11: J | AG11: ="CATALOGO!$"&AF11&"$3:$"&AF11&"$155" -> CATALOGO!$J$3:$J$155 | AJ11: 17 | AK11: Gerente / Gerente Región / Gerente País / Gerente Unidad de Negocio | AL11: Gerente de Cuenta | AM11: =IF(AK11="","",AK11)&IF(OR(AL11="",AK11=""),""," / ")&AL11 -> Gerente / Gerente Región / Gerente País / Gerente Unidad de Negocio / Gerente de Cuenta
B12: JEFE PROYECTO | C12: SUPERVISOR CULTIVO | D12: DIRECTOR TERMINALES CELULARES | E12: AUXILIAR AUDITORIA | F12: GERENTE ADMINISTRACIÓN VENTAS | G12: ARQUITECTO | H12: ADMINISTRADOR DROGUERÍA | I12: JEFE GOBIERNO CORPORATIVO | J12: GERENTE TESORERIA - TESORERO | K12: JEFE GESTION HUMANA | L12: JEFE SEGURIDAD HOTELERA | N12: ABOGADO JUNIOR | O12: GERENTE LOGISTICA | P12: GERENTE FABRICA O PLANTA | Q12: FOTOMECANICO | R12: JEFE MERCADEO | S12: COORDINADOR RELACIONES CON LA COMUNIDAD | U12: TÉCNICO ELECTRÓNICA II | V12: GERENTE PRODUCTO JR. LÍNEA ÉTICA | W12: JEFE DEPARTAMENTO MÉDICO | X12: JEFE CREDITOS EDUCATIVOS Y CARTERA | Y12: GERENTE FINANZAS | Z12: GERENTE OPERACIONES / PROCESAMIENTO INFORMACIÓN | AE12: GESTIÓN HUMANA | AF12: K | AG12: ="CATALOGO!$"&AF12&"$3:$"&AF12&"$155" -> CATALOGO!$K$3:$K$155 | AJ12: 16 | AK12: Gerente / Gerente Región / Gerente País / Gerente Unidad de Negocio | AL12: Gerente de Cuenta | AM12: =IF(AK12="","",AK12)&IF(OR(AL12="",AK12=""),""," / ")&AL12 -> Gerente / Gerente Región / Gerente País / Gerente Unidad de Negocio / Gerente de Cuenta
B13: JEFE PROCESOS | C13: SUPERVISOR RIEGO | D13: DIRECTOR TRANSMISIONES | F13: GERENTE VENTAS | G13: INGENIERO DISEÑO | H13: ADMINISTRADOR SUPERMERCADO | I13: GERENTE RELACIONES PUBLICAS - COMUNIC. | J13: GERENTE PRESUPUESTO | K13: JEFE CAPACITACION | L13: ASISTENTE RESERVAS Y/O HABITACIONES | O13: GERENTE DISTRIBUCIÓN | P13: GERENTE MEDIO AMBIENTE | Q13: PERIODISTA JUNIOR | R13: GERENTE PRODUCTO | S13: INGENIERO GEOLOGO | U13: ALMACENISTA PRODUCCIÓN | V13: DIRECTOR TÉCNICO | W13: JEFE INFORMACIÓN Y ESTADÍSTICA | X13: DIRECTOR DE OFICINA DE PUBLICACIONES | Y13: GERENTE FIDUCIA ADMINISTRACION Y PAGO | Z13: GERENTE SOPORTE Y TECNOLOGIA | AE13: HOTELERIA TURISMO Y RECREACIÓN | AF13: L | AG13: ="CATALOGO!$"&AF13&"$3:$"&AF13&"$155" -> CATALOGO!$L$3:$L$155 | AJ13: 15 | AK13: Director / Jefe | AL13: Especialista Sr / Ingeniero / Ejecutivo de Cuenta | AM13: =IF(AK13="","",AK13)&IF(OR(AL13="",AK13=""),""," / ")&AL13 -> Director / Jefe / Especialista Sr / Ingeniero / Ejecutivo de Cuenta
B14: JEFE ORGANIZACION Y METODOS | C14: COORDINADOR INCUBACIÓN | D14: GERENTE ESTADISTICAS E INFORMACION | F14: GERENTE SERVICIO AL CLIENTE | G14: INGENIERO CONTROL DE COSTOS | H14: ANALISTA TRADE MKARKETING | I14: JEFE COORDINADOR/ESPEC. ASUNTOS CORPORATIVOS | J14: DIRECTOR OFERTAS Y PRESUPUESTO | K14: JEFE COMUNICACIÓN INTERNA | L14: AUDITOR NOCTURNO | O14: GERENTE COMPRAS | P14: GERENTE SEGURIDAD INDUSTRIAL | Q14: ASISTENTE PLANCHAS | R14: GERENTE INVESTIGACION MERCADOS | S14: INGENIERO INTERVENTOR | U14: ELECTRICISTA EXPERTO | V14: GERENTE DIAGNOSTICA | W14: JEFE SANEAMIENTO AMBIENTAL | X14: DIRECTOR OFICINA COMUNICACIONES | Y14: GERENTE FIDUCIA INVERSION | Z14: GERENTE INVESTIGACION DLLO. TECNOLOGICO | AE14: I & D | AF14: M | AG14: ="CATALOGO!$"&AF14&"$3:$"&AF14&"$155" -> CATALOGO!$M$3:$M$155 | AJ14: 14 | AK14: Director / Jefe | AL14: Especialista Sr / Ingeniero / Ejecutivo de Cuenta | AM14: =IF(AK14="","",AK14)&IF(OR(AL14="",AK14=""),""," / ")&AL14 -> Director / Jefe / Especialista Sr / Ingeniero / Ejecutivo de Cuenta
B15: JEFE PROYECTOS | C15: SUPERVISOR DESPRESE | D15: GERENTE FRAUDES | F15: GERENTE REGIONAL (ZONA GEOGRAFICA DENTRO | G15: TRAMITADOR INMOBILIARIO | H15: ANALISTA CATEGORÍA | I15: JEFE RELACIONES PÚBLICAS | J15: GERENTE INVESTIGACION ECONOMICA | K15: DIRECTOR ADMINISTRACION SALARIOS | L15: COORDINADOR EVENTOS | O15: GERENTE IMPORTACIONES | P15: GERENTE MANTENIMIENTO | Q15: ASISTENTE ROTATIVA | R15: JEFE /COORDINADOR/ESPEC. INVESTIGACIÓN MERCADO | S15: INGENIERO PERFORACION SENIOR | U15: ELECTROMECÁNICO | V15: GERENTE DIVISIÓN FARMA | W15: JEFE UNIDAD SALUD | X15: DIRECTOR DEPTO BIENESTAR UNIVERSITARIO | Y15: GERENTE BANCA CORPORATIVA | Z15: JEFE TELECOMUNICACIONES | AE15: JURÍDICA | AF15: N | AG15: ="CATALOGO!$"&AF15&"$3:$"&AF15&"$155" -> CATALOGO!$N$3:$N$155 | AJ15: 13 | AK15: Director / Jefe | AL15: Especialista Sr / Ingeniero / Ejecutivo de Cuenta | AM15: =IF(AK15="","",AK15)&IF(OR(AL15="",AK15=""),""," / ")&AL15 -> Director / Jefe / Especialista Sr / Ingeniero / Ejecutivo de Cuenta
B16: GERENTE ADMINISTRATIVO (ZONA GEOGRAFICA) | C16: SUPERVISOR GRANJA | D16: GERENTE OPERACIONES TELECOMUNICACIONES | F16: GERENTE CAPACITACIÓN VENTAS SR. | G16: MAESTRO OBRA II | H16: PROMOTOR CONSUMO | I16: ANALISTA PLANEACION | J16: GERENTE PLANEACION CONTROL FINANCIERO | K16: JEFE BIENESTAR SOCIAL Y SALUD OCUPACIONAL | L16: SENIOR CLERK | O16: GERENTE IMPORTACIONES Y EXPORTACIONES | P16: DIRECTOR GESTION AMBIENTAL | Q16: AUXILIAR ROTATIVA | R16: JEFE INVESTIGACION MERCADOS | S16: INGENIERO YACIMIENTOS | U16: MECÁNICO AJUSTADOR EXPERTO | V16: GERENTE DIVISIÓN HOSPITALARIA | W16: ANESTESIOLOGO | X16: DIRECTOR RESTAURANTE | Y16: GERENTE REGIONAL | Z16: JEFE SOPORTE TECNICO | AE16: LOGÍSTICA Y SUMINISTROS | AF16: O | AG16: ="CATALOGO!$"&AF16&"$3:$"&AF16&"$155" -> CATALOGO!$O$3:$O$155 | AJ16: 12 | AK16: Director / Jefe | AL16: Especialista / Ingeniero / Ejecutivo de Cuenta | AM16: =IF(AK16="","",AK16)&IF(OR(AL16="",AK16=""),""," / ")&AL16 -> Director / Jefe / Especialista / Ingeniero / Ejecutivo de Cuenta
B17: JEFE ./COORDINADOR ADMINISTRATIVO | C17: CABO CAMPO | D17: JEFE DEPARTAMENTO GESTION RED | F17: GERENTE CUENTA | G17: TOPÓGRAFO | H17: VENDEDOR(A) DROGUERÍA | I17: ANALISTA CORPORATIVO | J17: GERENTE IMPUESTOS | K17: JEFE RELACIONES LABORALES/SINDICALES | L17: SOUS CHEFF | O17: JEFE REGULACIÓN Y REGISTRO | P17: GERENTE ASEGURAMIENTO CALIDAD | R17: COORDINADOR EVENTOS | S17: GEOFISICO | U17: MECÁNICO MANTENIMIENTO | V17: GERENTE DIVISIÓN NUTRICIÓN | W17: BACTERIOLOGO | X17: DIRECTOR CARRERA | Y17: GERENTE BANCA PERSONAL | Z17: JEFE SEGURIDAD SISTEMAS | AE17: MANUFACTURA E INDUSTRIA | AF17: P | AG17: ="CATALOGO!$"&AF17&"$3:$"&AF17&"$155" -> CATALOGO!$P$3:$P$155 | AJ17: 11 | AK17: Coordinador | AL17: Especialista / Ingeniero / Ejecutivo de Cuenta | AM17: =IF(AK17="","",AK17)&IF(OR(AL17="",AK17=""),""," / ")&AL17 -> Coordinador / Especialista / Ingeniero / Ejecutivo de Cuenta
B18: JEFE CENTRO DOCUMENTACION | C18: CABO COSECHA | D18: JEFE INSTALACIONES | F18: DIRECTOR / JEFE COMERCIAL | G18: AUXILIAR INGENIERIA | H18: CAJERO SUPERMERCADO | I18: ASISTENTE PRESIDENTE / VICEPRESIDENTE | J18: DIRECTOR FINANCIERO | K18: DIRECTOR PERSONAL | L18: BARMAN | O18: JEFE PLANEACION Y CONTROL INVENTARIOS | P18: GERENTE CONTROL CALIDAD | R18: ANALISTA PUBLICIDAD | S18: GEOFÍSICO | U18: OPERARIO EXPERTO MÁQUINAS PRODUCCIÓN | V18: DIRECTOR CIENTÍFICO (LABORATORIOS) | W18: DIETISTA - NUTRICIONISTA | X18: DIRECTOR CONSULTORIO JURÍDICO | Y18: DIRECTOR TARJETA DE CREDITO | Z18: JEFE /COORDINADOR/ESPEC. INFRAESTRUCTURA | AE18: MEDIOS | AF18: Q | AG18: ="CATALOGO!$"&AF18&"$3:$"&AF18&"$155" -> CATALOGO!$Q$3:$Q$155 | AJ18: 10 | AK18: Coordinador | AL18: Especialista / Ingeniero / Ejecutivo de Cuenta | AM18: =IF(AK18="","",AK18)&IF(OR(AL18="",AK18=""),""," / ")&AL18 -> Coordinador / Especialista / Ingeniero / Ejecutivo de Cuenta
B19: JEFE SERVICIOS GENERALES | C19: MONITOR CORTE CAÑA | D19: JEFE SOFTWARE ESPECIALIZADO | F19: GERENTE COMERCIAL ZONA | G19: AUXILIAR RESIDENTE | H19: MERCADERISTA | I19: ASISTENTE RELACIONES PUBLICAS - COMUNIC. | J19: GERENTE CREDITO | K19: JEFE PERSONAL | L19: CAPITÁN BOTONES | O19: JEFE LOGÍSTICA Y OPERACIONES | P19: DIRECTOR CALIDAD | R19: CREATIVO | S19: GEÓLOGO | U19: OPERARIO III PRODUCCIÓN | V19: DIRECTOR MEDICO | W19: FISIOTERAPEUTA | X19: JEFE ADMISIONES Y REGISTRO | Y19: GERENTE TARJETA CREDITO | Z19: JEFE INFRAESTRUCTURA | AE19: MERCADEO | AF19: R | AG19: ="CATALOGO!$"&AF19&"$3:$"&AF19&"$155" -> CATALOGO!$R$3:$R$155 | AJ19: 9 | AK19: Coordinador | AL19: Analista Sr / Ingeniero / Asesor Comercial | AM19: =IF(AK19="","",AK19)&IF(OR(AL19="",AK19=""),""," / ")&AL19 -> Coordinador / Analista Sr / Ingeniero / Asesor Comercial
B20: COORDINADOR/ESPEC. SEGURIDAD Y PREVENCIÓN PERDIDAS | C20: MONTADOR PRIMERA | D20: CONSULTOR IT | F20: GERENTE DISTRITO O SUCURSAL | G20: MAESTRO OBRA I | H20: SURTIDOR SUPERMERCADO | J20: GERENTE COSTOS | K20: COORDINADOR/ESPEC./JEFERECLUTAMIENTO Y SELECCIÓN | L20: CAPITÁN ROOM SERVICE | O20: JEFE ADMINISTRACIÓN DEL RIESGO TERRESTRE | P20: JEFE SEGURIDAD INDUSTRIAL | R20: DISEÑADOR GRÁFICO | S20: INGENIERO FACILIDADES | U20: OPERARIO MAQUINARIA PESADA | V20: GERENTE ASUNTOS REGULATORIOS | W20: JEFE DEPARTAMENTO ENFERMERÍA | X20: DIRECTOR BIENESTAR UNIVERSITARIO | Y20: DIRECTOR INGENIERIA FINANCIERA | Z20: JEFE PROYECTOS SISTEMAS | AE20: MINERIA, ENERGIA E HIDROCARBUROS | AF20: S | AG20: ="CATALOGO!$"&AF20&"$3:$"&AF20&"$155" -> CATALOGO!$S$3:$S$155 | AJ20: 8 | AK20: Supervisor | AL20: Analista Sr / Técnico / Operario Especializado / Ingeniero / Asesor Comercial | AM20: =IF(AK20="","",AK20)&IF(OR(AL20="",AK20=""),""," / ")&AL20 -> Supervisor / Analista Sr / Técnico / Operario Especializado / Ingeniero / Asesor Comercial
B21: JEFE SEGURIDAD FISICA | C21: OPERADOR CENTRIFUGAS PRIMERA | D21: CONSULTOR PRE-VENTA (PRODUCTO/TÉCNICO) | F21: JEFE TELEMARKETING - ACTIVO | G21: AUXILIAR TECNICO | H21: AUXILIAR CATEGORÍA | J21: CONTRALOR | K21: PSICOLOGO | L21: CAPITÁN SERVICIO | O21: JEFE CENTRO DISTRIBUCIÓN | P21: JEFE SEGURIDAD LABORAL | R21: ANALISTA MERCADEO | S21: INGENIERO PERFORACIONES | U21: SOLDADOR EXPERTO | V21: GERENTE DIVISIÓN AGROQUÍMICA | W21: JEFE FARMACIA | X21: ADMINISTRADOR SALA DE COMPUTO | Y21: GERENTE PREVENCIÓN | Z21: JEFE SAP | AE21: OPERACIONES | AF21: T | AG21: ="CATALOGO!$"&AF21&"$3:$"&AF21&"$155" -> CATALOGO!$T$3:$T$155 | AJ21: 7 | AK21: Supervisor | AL21: Analista / Técnico / Operario Especializado / Ingeniero / Asesor Comercial | AM21: =IF(AK21="","",AK21)&IF(OR(AL21="",AK21=""),""," / ")&AL21 -> Supervisor / Analista / Técnico / Operario Especializado / Ingeniero / Asesor Comercial
B22: SUPERVISOR SEGURIDAD Y VIGILANCIA | C22: OPERADOR CRISTALIZADORES | D22: COORDINADOR IMPLEMENTACIÓN | F22: JEFE SERVICIO AL CLIENTE | G22: AYUDANTE ENTENDIDO | J22: GERENTE CONTABILIDAD | K22: COORDINADOR NOMINA | L22: CORTADOR CARNES - BOUCHER | O22: JEFE DESPACHOS | P22: JEFE PRODUCCION | R22: ANALISTA SR PRODUCTOS | S22: INGENIERO PRODUCCIÓN | U22: INSPECTOR CALIDAD | V22: JEFE PRODUCCIÓN - CREMAS | W22: MEDICO ESPECIALISTA | X22: BIBLIOTECOLOGO | Y22: GERENTE NACIONAL SINIESTROS | Z22: JEFE CENTRO COMPUTO | AE22: OPERARIOS | AF22: U | AG22: ="CATALOGO!$"&AF22&"$3:$"&AF22&"$155" -> CATALOGO!$U$3:$U$155 | AJ22: 6 | AK22: Supervisor | AL22: Analista / Técnico / Operario Especializado / Asesor Comercial | AM22: =IF(AK22="","",AK22)&IF(OR(AL22="",AK22=""),""," / ")&AL22 -> Supervisor / Analista / Técnico / Operario Especializado / Asesor Comercial
B23: JEFE SUCURSAL | C23: OPERADOR MESA CAÑA | D23: COORDINADOR TÉCNICO INTERCONEXIÓN | F23: JEFE RELACIONES PÚBLICAS - COMUNICACIONES | G23: OFICIAL DE CONSTRUCCION II | J23: DIRECTOR CONTABILIDAD | K23: JEFE NOMINA | L23: HOUSE MAN | O23: JEFE LOGISTICA | P23: JEFE PLANEACION Y CONTROL PRODUCCIÓN | R23: ANALISTA MERCADEO / INVESTIGACION DE MERCADOS | S23: INGENIERO RESERVORIO | U23: TORNERO | V23: JEFE PRODUCCIÓN - LÍQUIDOS | W23: MEDICO GENERAL | X23: COORDINADOR ACADEMICO FACULTAD | Y23: GERENTE REASEGURO | Z23: JEFE PROCESAMIENTO DATOS | AE23: QUÍMICO Y FARMA | AF23: V | AG23: ="CATALOGO!$"&AF23&"$3:$"&AF23&"$155" -> CATALOGO!$V$3:$V$155 | AJ23: 5 | AL23: Auxiliar/Operario III / Representante de Ventas Sr | AM23: =IF(AK23="","",AK23)&IF(OR(AL23="",AK23=""),""," / ")&AL23 -> Auxiliar/Operario III / Representante de Ventas Sr
B24: PROFESIONAL SENIOR | C24: OPERADOR MOLINOS | D24: ANALISTA GERENCIA DE PROYECTOS - ESPECIALISTA | F24: JEFE CAPACITACIÓN VENTAS | G24: ALBAÑIL | J24: JEFE TESORERIA | K24: COORDINADOR/ESPEC./JEFEENTRENAMIENTO Y DESARROLLO | L24: JEFE TURNO | O24: JEFE COMPRAS | P24: JEFE PLANEACION PRODUCCION | R24: ASISTENTE PROMOCION PUBLICITARIA | S24: LÍDER CONTRATOS | U24: AUXILIAR VEHICULO | V24: ASESOR MEDICO | W24: NUTRICIONISTA | X24: COORDINADOR AREA | Y24: GERENTE TÉCNICO | Z24: JEFE INVESTIGACION TECNOLOGICA | AE24: SERVICIOS DE SALUD | AF24: W | AG24: ="CATALOGO!$"&AF24&"$3:$"&AF24&"$155" -> CATALOGO!$W$3:$W$155 | AJ24: 4 | AL24: Auxiliar / Operario II / Representante de Ventas Sr | AM24: =IF(AK24="","",AK24)&IF(OR(AL24="",AK24=""),""," / ")&AL24 -> Auxiliar / Operario II / Representante de Ventas Sr
B25: JEFE ARCHIVO | C25: AYUDANTE MOLINOS | D25: CONSULTOR CONTRATOS, LICITACIONES Y PROPUESTAS - JR. | F25: JEFE ADMINISTRACION VENTAS | G25: AYUDANTE OBRA | J25: JEFE SEGUROS | K25: COORDINADOR/ESPEC./JEFECOMPENSACIÓN Y BENEFICIOS | L25: MAITRE | O25: DIRECTOR O JEFE COMERCIO EXTERIOR | P25: JEFE MANTENIMIENTO | R25: ASISTENTE MERCADEO | S25: LÍDER GEOLOGÍA | U25: CONDUCTOR VEHÍCULO LIVIANO | V25: DIRECTOR DIVISIÓN DIAGNOSTICO | W25: ODONTOLOGO ESPECIALISTA | X25: COORDINADOR INVESTIGACION | Y25: GERENTE SUCURSAL | Z25: JEFE SISTEMAS | AE25: SERVICIOS EDUCATIVOS | AF25: X | AG25: ="CATALOGO!$"&AF25&"$3:$"&AF25&"$155" -> CATALOGO!$X$3:$X$155 | AJ25: 3 | AL25: Auxiliar / Operario I / Representante de Ventas Jr | AM25: =IF(AK25="","",AK25)&IF(OR(AL25="",AK25=""),""," / ")&AL25 -> Auxiliar / Operario I / Representante de Ventas Jr
B26: SECRETARIA EJECUTIVA PRESIDENCIA | C26: AYUDANTE TACHOS | D26: ARCHIVO | F26: INGENIERO VENTAS | G26: OFICIAL DE CONSTRUCCION I | J26: JEFE RIESGOS | K26: ABOGADO | L26: TELEFONISTA | O26: JEFE ADUANA | P26: JEFE MANTENIMIENTO ELECTRICO | R26: AUXILIAR AYUDAS AUDIOVISUALES | S26: LIDER PERFORACIÓN | U26: HERRAMENTISTA II | V26: JEFE ACABADO | W26: ODONTOLOGO GENERAL | X26: COORDINADOR POSTGRADO | Y26: GERENTE SUCURSAL PRINCIPAL | Z26: INGENIERO TELECOMUNICACIONES | AE26: SERVICIOS FINANCIEROS Y SEGUROS | AF26: Y | AG26: ="CATALOGO!$"&AF26&"$3:$"&AF26&"$155" -> CATALOGO!$Y$3:$Y$155 | AJ26: 2 | AL26: Auxiliar / Operario I / Representante de Ventas Jr | AM26: =IF(AK26="","",AK26)&IF(OR(AL26="",AK26=""),""," / ")&AL26 -> Auxiliar / Operario I / Representante de Ventas Jr
B27: ANALISTA PROYECTOS | C27: CONDUCTOR REMOLCADOR CAÑA | D27: ASESOR SUSCRIPCIONES | F27: VENDEDOR TÉCNICO/ENGIENERO | J27: JEFE PRESUPUESTO | K27: REPRESENTANTE RELACIONES LABORALES | L27: ASISTENTE ALIMENTOS Y BEBIDAS | O27: JEFE EXPORTACIONES | P27: JEFE CONTROL CALIDAD | R27: AUXILIAR MERCADEO | S27: LIDER RESERVORIOS | U27: OPERARIO ENVOLTURA | V27: JEFE DIVISIÓN SERVICIOS HOSPITALARIOS | W27: ORTOPEDISTA | X27: DECANO TIPO B | Y27: GERENTE MESA CONTROL | Z27: DISEÑADOR GRAFICO WEB | AE27: TECNOLOGÍA E INFORMÁTICA | AF27: Z | AG27: ="CATALOGO!$"&AF27&"$3:$"&AF27&"$155" -> CATALOGO!$Z$3:$Z$155 | AJ27: 1 | AL27: Operario I / Ayudante | AM27: =IF(AK27="","",AK27)&IF(OR(AL27="",AK27=""),""," / ")&AL27 -> Operario I / Ayudante
B28: ANALISTA PROCESOS | C28: MONTADOR SEGUNDA | D28: DIGITADOR CORRECTOR | F28: REPRESENTANTE TELE-VENTAS | J28: JEFE PLANEACION FINANCIERA | K28: ANALISTA RECLUTAMIENTO Y SELECCIÓN | L28: PRIMER COCINERO | O28: JEFE IMPORTACIONES | P28: JEFE LABORATORIO | R28: AUXILIAR MERCADEO Y VENTAS | S28: SUPERVISOR FACILIDADES | U28: OPERARIO PREPARADOR PRODUCTOS QUIMICOS | V28: JEFE PROCESOS | W28: PATÓLOGO | X28: INVESTIGADOR | Y28: GERENTE EXÁMENES MÉDICOS | Z28: WEB MASTER | AE28: TEXTILES CONFECCIONES Y CALZADO | AF28: AA | AG28: ="CATALOGO!$"&AF28&"$3:$"&AF28&"$155" -> CATALOGO!$AA$3:$AA$155
B29: ANALISTA ORGANIZACION Y METODOS | C29: AYUDANTE VACUNACIÓN | F29: SUPERVISOR TELEMARKETING - ACTIVO | J29: JEFE /COORDINADOR/ESPEC. RELACIONES CON INVERSIONISTAS | K29: ASISTENTE SALUD OCUPACIONAL | L29: AUXILIAR BAR | O29: JEFE IMPORTACIONES Y EXPORTACIONES | P29: JEFE LABORATORIO/CONTROL CALIDAD | S29: SUPERVISOR GEOLOGÍA | U29: OPERADOR I | V29: COORDINADOR/SUPV. FARMACOVIGILÂNCIA | W29: PEDÍATRA | X29: JEFE ADQUISIONES BIBLIOTECA | Y29: GERENTE PRESTADORES MÉDICOS | Z29: INGENIERO SOPORTE TECNICO | AE29: VEHÍCULOS Y PARTES | AF29: AB | AG29: ="CATALOGO!$"&AF29&"$3:$"&AF29&"$155" -> CATALOGO!$AB$3:$AB$155
B30: ANALISTA ADMINISTRATIVO | C30: GALPONEROS GRANJA | F30: COORDINADOR ATENCIÓN AL CONSUMIDOR | J30: JEFE INVERSIONES | K30: SUPERVISOR SEGURIDAD INDUSTRIAL/ SALUD OCUPACIONAL | L30: AUXILIAR COCINA | O30: JEFE OPERACIONES INTERNACIONALES | P30: JEFE INGENIERIA | S30: SUPERVISOR OPERACIONES | U30: OPERADOR II | V30: INGENIERO CERTIFICACIÓN | W30: PSIQUIATRA | X30: JEFE PROCESOS TECNICOS BIBLIOTECA | Y30: GTE INGENIEROS INSPECCIÓN | Z30: SUPERVISOR HELP DESK
B31: ASISTENTE ADMINISTRATIVO | F31: INGENIERO SERVICIOS TÉCNICOS (CAMPO) | J31: JEFE IMPUESTOS | K31: ANALISTA RECURSOS HUMANOS (GENERALISTA) | L31: AUXILIAR COCINA I | O31: GERENTE ALMACÉN | P31: JEFE INGENIERIA INDUSTRIAL | S31: SUPERVISOR PRODUCCIÓN | U31: AYUDANTE ALMACÉN | V31: MICROBIÓLOGO | W31: ENFERMERA | X31: JEFE SERVICIOS AL PUBLICO BIBLIOTECA | Y31: GERENTE SEGUROS GENERALES | Z31: ADMINISTRADOR BASE DE DATOS
B32: ESCOLTA PERSONAL | F32: JEFE CALL CENTER | J32: JEFE FINANCIERO | K32: ANALISTA NOMINA | L32: AUXILIAR HABITACIONES | O32: COORDINADOR REGULATORIO | P32: JEFE PLANTA | S32: SUPERVISOR RESERVORIO | U32: AYUDANTE MANTENIMIENTO | V32: QUIMICO- FARMACEUTICO | W32: PSICÓLOGO CLÍNICO | X32: PROFESOR ASISTENTE TIPO A | Y32: GERENTE OPERACIONES | Z32: ADMINISTRADOR REDES
B33: RECEPCIONISTA | F33: JEFEPLANEACION VENTAS | J33: JEFE CREDITO Y COBRANZAS | K33: ANALISTA CAPACITACIÓN Y DESARROLLO | L33: AUXILIAR LAVANDERÍA | O33: COORDINADOR DESARROLLO PROVEEDORES | P33: JEFE /COORDINADOR/ESPEC. MEDIO AMBIENTE | S33: INGENIERO HSEQ | U33: AYUDANTE MECÁNICA | V33: REP. VENTAS - ESPECIALIDADES | W33: TÉCNICO RAYOS X | X33: PROFESOR ASOCIADO TIPO A | Y33: DIRECTOR FONDO COMUN | Z33: INGENIERO REDES
B34: RECEPCIONISTA BILINGUE | F34: ANALISTA CUENTAS CLAVES | J34: JEFE COSTOS | K34: ANALISTA COMUNICACIONES INTERNAS | L34: AUXILIAR MINIBAR | O34: INGENIERO DESARROLLO PROVEEDORES | P34: JEFE AMBIENTAL | S34: TÉCNICO ELECTRICISTA INDUSTRIA | U34: ELECTRICISTA INSTALADOR | V34: REP. VENTAS - HOSPITALES | W34: TÉCNICO TERAPIA OCUPACIONAL | X34: PROFESOR CATEDRA PREGRADO TIPO A | Y34: GERENTE PRODUCTO O NEGOCIO FIDUCIARIO | Z34: COORDINADOR/JEFEOPERACIÓN SISTEMAS
B35: SECRETARIA BILINGÜE | F35: REPRESENTANTE VENTAS SENIOR | J35: JEFE CONTABILIDAD | K35: ANALISTA COMPENSACIÓN Y BENEFICIOS | L35: CONSERJE | O35: COORDINADOR/JEFEPLANEACION LOGÍSTICA | P35: JEFE ./COORDINADOR ESP. ASEGURAMIENTO CALIDAD | S35: TÉCNICO ELECTRÓNICA | U35: EMPACADOR PRODUCTOS | V35: JEFE FÍSICO - QUÍMICO | W35: CAPELLÁN | X35: PROFESOR CATEDRA PREGRADO TIPO B | Y35: GERENTE CREDITO PERSONAS | Z35: INGENIERO SISTEMAS
B36: SECRETARIA EJECUTIVA | F36: SUPERVISOR VENTAS | J36: JEFE CARTERA | K36: ASISTENTE / ANALISTA COMPENSACIÓN | L36: LENCERÍA - COSTURERA | O36: JEFE MATERIALES | P36: JEFE ASEGURAMIENTO CALIDAD | S36: TÉCNICO EXPLORACIÓN | U36: OPERARIO I PRODUCCIÓN | V36: JEFE LÍQUIDOS | W36: PROMOTORA SOCIAL | X36: PROFESOR INSTRUCTOR TIPO A | Y36: GERENTE CREDITO CORPORATIVO | Z36: INGENIERO DESARROLLO APLICACIONES
B37: SECRETARIA GENERAL | F37: OPER. TELEMARKETING - ACTIVO | J37: COORDINADOR/ESPEC./JEFEPRESUPUESTOS | K37: ASISTENTE BIENESTAR SOCIAL | L37: MESERO | O37: COORDINADOR ABASTECIMIENTO Y LOGÍSTICA | P37: INGENIERO SEGURIDAD LABORAL | S37: TÉCNICO MECÁNICO | U37: OPERARIO II PRODUCCIÓN | V37: JEFE MICROBIOLOGÍA | W37: AYUDANTE ENFERMERÍA | X37: PROFESOR TITULAR TIPO A | Y37: GERENTE CONTROL PERDIDAS | Z37: INGENIERO INFORMÁTICA
B38: PROFESIONAL EN ENTRENAMIENTO | F38: ANALISTA SERVICIOS AL CLIENTE | J38: COORDINADOR/ESPEC./JEFEPLANEACION/ANAL. FINANCIERA | K38: ANALISTA ADMINISTRACIÓN RH | L38: MESEROS | O38: SUPERVISOR LOGÍSTICA Y OPERACIONES | P38: INGENIERO PRODUCCION | S38: TECNÓLOGO PRODUCCIÓN | U38: AUXILIAR CALIDAD | V38: JEFE SOLUCIONES | W38: INSTRUMENTADOR | X38: VICEDECANO | Y38: GTE COMERCIAL CANAL RETAIL | Z38: DISEÑADOR WEB
B39: PROFESIONAL JUNIOR | F39: ANALISTA DESARROLLO NEGOCIOS | J39: NEGOCIADOR | K39: ASISTENTE GESTION HUMANA | L39: PASTELERO - PANADERO | O39: COORDINADOR/JEFEDISTRIBUCIÓN | P39: INGENIERO PROCESOS | S39: SUPERVISOR ADMINISTRATIVO | U39: AUXILIAR LABORATORIO | V39: JEFE TABLETERIA | W39: RADIÓLOGO | X39: JEFE PRESUPUESTO (EDUCACION) | Y39: GERENTE CONVENIOS | Z39: EDITOR WEB
B40: SUPERNUMERARIO NO FINANCIERO | F40: ANALISTA CAPACITACIÓN VENTAS | J40: COORDINADOR/ESPEC./JEFEIMPUESTOS | K40: ASISTENTE ADMINISTRACIÓN RH | L40: PORTERO | O40: COMPRADOR TÉCNICO | P40: SUPERVISOR PROCESOS | S40: ASISTENTE AYUDAS A LA COMUNIDAD | U40: AUXILIAR BODEGA | V40: JEFE VALIDACIONES | W40: REGENTE DE FARMACIA | X40: COORDINADOR PROMOCION UNIVERSITARIA | Y40: GERENTE ZONA | Z40: ANALISTA SOPORTE - TI
B41: CONDUCTOR GERENCIA | F41: ANALISTA ATENCIÓN AL CONSUMIDOR | J41: COORDINADOR /ESPEC./JEFEFINANZAS | K41: AUXILIAR GESTION HUMANA | L41: PREPARADOR ALIMENTOS | O41: JEFE ALMACEN | P41: INGENIERO MANTENIMIENTO | S41: CONDUCTOR CAMIÓN PESADO | U41: AUXILIAR DESPACHOS | V41: SUPERVISOR AGROPECUARIO | W41: CONDUCTOR AMBULANCIA | X41: COORDINADOR CULTURAL Y DEPORTIVO | Y41: GERENTE COASEGUROS | Z41: ASISTENTE HELP DESK
B42: AUXILIAR ASEO Y CAFETERÍA | F42: ANALISTA SERVICIOS TÉCNICOS AL CLIENTE | J42: COORDINADOR/ESPEC./JEFECUENTAS PAGAR/RECIBIR | K42: AUXILIAR NOMINA | L42: STEWARD | O42: JEFE BODEGA PRODUCTO TERMINADO | P42: INGENIERO MANTENIMIENTO MECANICO | S42: OPERADOR PRODUCCIÓN | V42: VISITADOR MEDICO | W42: AUXILIAR ENFERMERIA | X42: COORDINADOR CORRESPONDENCIA | Y42: GERENTE BANCASEGUROS | Z42: TÉCNICO TRANSMISIÓN DATOS Y VOZ
B43: AUXILIAR ASEO Y CAFETERÍA | F43: ANALISTA COMERCIAL | J43: COORDINADOR/ESPEC./JEFECRÉDITO Y COBRANZA | K43: AUXILIAR ADMINISTRACIÓN RH | L43: AMA DE LLAVES | O43: JEFE EMPAQUE | P43: SUPERVISOR MANTENIMIENTO | S43: HERRAMENTISTA | V43: ANALISTA FARMACOVIGILÂNCIA | W43: AUXILIAR FARMACIA | X43: SECRETARIO ACADÉMICO | Y43: GTE PROC. EMISIONES ARP | Z43: ANALISTA SEGURIDAD SISTEMAS
B44: MENSAJERO | F44: ANALISTA PLANEACION VENTAS PL. | J44: COORDINADOR/ESPEC./JEFECOSTOS | L44: BOTONES | O44: JEFE MERCANCIAS | P44: MICROBIOLOGO | S44: MONTACARGUISTA | V44: COORDINADOR SERVICIOS HOSPITALARIOS | W44: AUXILIAR ODONTOLOGIA | X44: ADMINISTRADOR PLANTA FISICA | Y44: GERENTE TÉCNICO ACTUARIAL | Z44: ANALISTA NEGOCIOS - ERP
B45: MENSAJERO EXTERNO | F45: ANALISTA VENTAS | J45: CONTADOR | L45: CAMARERA | O45: ANALISTA REGULACIÓN Y REGISTRO | P45: DISEÑADOR INDUSTRIAL | S45: OPERADOR GENERACIÓN ELÉCTRICA | V45: ANALISTA FÍSICO - QUÍMICO | W45: CAMILLERO | X45: SECRETARIO ADMINISTRATIVO | Y45: GERENTE INDEMNIZACION | Z45: ANALISTA NEGOCIOS - TI
B46: MENSAJERO INTERNO | F46: EJECUTIVO VENTAS CLAVES | J46: COORDINADOR /ESPEC.CARTERA | O46: ANALISTA PLANEACION LOGÍSTICA | P46: INGENIERO PROYECTOS INDUSTRIALES | S46: OPERADOR II | V46: BACTERIÓLOGO (LABORATORIOS) | X46: PROFESOR COLEGIO | Y46: GERENTE REASEGUROS | Z46: ASISTENTE PROYECTOS SISTEMAS
B47: VIGILANTE/PORTERO | F47: VENDEDOR TECNICO | J47: JEFE FACTURACION | O47: ANALISTA CONTROL DE INVENTARIOS | P47: INSTRUMENTISTA/METROLOGO | S47: OPERADOR III | V47: ANALISTA INVESTIGACIÓN CLÍNICA | X47: ANALISTA PRESUPUESTO | Y47: GERENTE SUSCRIPCION | Z47: TÉCNICO OPERACIONES
B48: SECRETARIA AUXILIAR | F48: ADMINISTRADOR PUNTO DE VENTA | J48: ANALISTA TESORERIA | O48: ANALISTA ABASTECIMIENTO Y LOGÍSTICA | P48: INGENIERO MEDIO AMBIENTE PL. | S48: OPERADOR I | V48: AUXILIAR LABORATORIO | X48: ANALISTA CREDITOS EDUCATIVOS | Y48: JEFE DEPARTAMENTO EXTRANJERO | Z48: ANALISTA PROGRAMADOR
B49: AUXILIAR ADMINISTRATIVO | F49: IMPULSADOR | J49: ANALISTAS SEGUROS | O49: ASISTENTE LOGÍSTICA Y OPERACIONES | P49: INGENIERO CALIDAD | V49: AUXILIAR GRANULACIÓN | X49: PROFESOR HORA CÁTEDRA | Y49: JEFE MESA DINERO | Z49: ANALISTA SISTEMAS
B50: AUXILIAR ARCHIVO | F50: PROMOTOR SERVICIOS | J50: ANALISTA RIESGOS | O50: ANALISTA DISTRIBUCIÓN | P50: ANALISTA PRODUCCION | X50: PROFESOR POSTGRADO HORA CÁTEDRA | Y50: JEFE SECCIÓN FIDUCIARIA | Z50: ANALISTA SISTEMAS
B51: CONDUCTOR | F51: REPRESENTANTE VENTAS JUNIOR | J51: ANALISTA PRESUPUESTOS | O51: ANALISTA TRANSPORTE | P51: SUPERVISOR PRODUCCION | X51: PROFESOR POSTGRADO TIEMPO COMPLETO | Y51: JEFE TÉCNICO | Z51: PROGRAMADOR
B52: CONDUCTOR SERVICIOS GENERALES | F52: VENDEDOR SALA | J52: ANALISTA PLANEACIÓN FINANCIERA | O52: ANALISTA ADMINISTRACIÓN CONTRATOS | P52: ANALISTA PLANIFICACIÓN Y CONTROL PL. | X52: PROFESOR TIEMPO COMPLETO | Y52: DIRECTOR TARJETA CRÉDITO | Z52: DIAGRAMADOR
B53: AUXILIAR ORG Y MÉTODOS | F53: VENDEDOR TRAINEE | J53: ANALISTA SSR. INVERSIONES | O53: ANALISTA COMPRAS | P53: ANALISTA MANTENIMIENTO | X53: ASISTENTE PUBLICACIONES | Y53: JEFE TARJETA CREDITO | Z53: TÉCNICO HELPDESK SR.
B54: AUXILIAR MANTENIMIENTO | F54: ASISTENTE SERVICIO AL CLIENTE | J54: ANALISTA IMPUESTOS | O54: ASISTENTE COMPRAS | P54: ANALISTA LABORATORIO | X54: COORDINADOR BIENESTAR UNIVERSITARIO | Y54: JEFE DPTO SUSCRIPCIÓN | Z54: DATA ENTRY
B55: OPERARIO ASEO Y/O LIMPIEZA | F55: AGENTE ATENCIÓN AL CONSUMIDOR | J55: ANALISTA FINANCIERO | O55: ANALISTA COMERCIO EXTERIOR | P55: ANALISTA AMBIENTAL | X55: ASISTENTE ÁREA DOCENTE RECURSOS HUMANOS | Y55: JEFE PREVENCIÓN | Z55: OPERADOR COMPUTADOR
F56: TÉCNICO SERVICIOS (CAMPO) | J56: ANALISTA CUENTAS PAGAR/RECIBIR | O56: ANALISTA EXPORTACIONES | P56: ANALISTA CALIDAD | X56: ASISTENTE DECANO | Y56: JEFE INVESTIGACIONES CRÉDITO | Z56: TECNICO PROGRAMADOR
F57: ASISTENTE ADMINISTRATIVO VENTAS PL. | J57: ANALISTA FACTURACIÓN | O57: ANALISTA IMPORTACIONES Y EXPORTACIONES | P57: ANALISTA CONTROL DE CALIDAD | X57: ASISTENTE POSTGRADO | Y57: JEFE DPTO SINIESTROS | Z57: DIGITADOR
F58: AUXILIAR VENTAS | J58: ANALISTA CREDITO | O58: SUPERVISOR BODEGA | P58: ASISTENTE CALIDAD | X58: ASISTENTE AUDIOVISUALES | Y58: JEFE REASEGURO
F59: AGENTE DE TELE-VENTAS | J59: ANALISTA CRÉDITO Y COBRANZA | O59: TÉCNICO LOGÍSTICA | P59: TÉCNICO SEGURIDAD LABORAL | X59: AUXILIAR SOPORTE SISTEMAS | Y59: JEFE PATRIMONIALES
F60: AUXILIAR SERVICIO AL CLIENTE | J60: ANALISTA/PROFESIONAL COSTOS | O60: ANALISTA LOGISTICA | P60: ASISTENTE PLANEACION PRODUCCION | X60: AUXILIAR BIBLIOTECA | Y60: DIRECTOR DE OPERACIONES
F61: ASESOR CALL CENTER | J61: ANALISTA CONTABILIDAD | O61: SUPERVISOR TRÁFICO | P61: TECNICO ELECTROMECÁNICO | X61: AUXILIAR PUBLICACIONES | Y61: JEFE GIROS Y REMESAS
J62: ANALISTA CARTERA | O62: ASISTENTE IMPORTACIONES - EXPORTACIONES | P62: TECNICO MANTENIMIENTO | Y62: SUBGERENTE OFICINA - JEFE OPERATIVO
J63: CAJERO SERVICIOS | O63: ASISTENTE OPERACIONES INTERNACIONALES | P63: ASISTENTE LABORATORIO | Y63: JEFE PRESTADORES MÉDICOS
J64: ASISTENTE FINANCIERO | O64: TRAMITADOR ADUANA | P64: TÉCNICO LABORATORIO | Y64: MEDICO
J65: COBRADOR | O65: ALMACENISTA MATERIALES | P65: TÉCNICO CALIDAD | Y65: JEFE INGENIEROS INSPECCIÓN
J66: ASISTENTE COSTOS | O66: ASISTENTE ALMACEN | P66: AUXILIAR DE SALUD OCUPACIONAL Y SEGURIDAD INDUSTRIAL | Y66: DIRECTOR INMUEBLES
J67: ASISTENTE CONTABILIDAD | O67: AUXILIAR CONTROL INVENTARIOS | P67: AUXILIAR PRODUCCIÓN | Y67: JEFE CAPTACIONES
J68: ASISTENTE CARTERA | O68: AUXILIAR DISTRIBUCIÓN | Y68: JEFE PROCESO OPERACIONES
J69: ASISTENTE FACTURACION | O69: AUXILIAR COMPRAS | Y69: JEFE PROYECTOS FIDUCIARIOS
J70: AUXILIAR TESORERIA | O70: AUXILIAR COMERCIO EXTERIOR | Y70: JEFE CREDITO PERSONAS
J71: AUXILIAR RIESGOS | O71: AUXILIAR DE IMPORTACIONES | Y71: JEFE CREDITO CORPORATIVO
J72: AUXILIAR INVERSIONES | O72: AUXILIAR EXPORTACIONES | Y72: JEFE CONVENIOS
J73: AUXILIAR IMPUESTOS | O73: AUXILIAR ALMACÉN | Y73: JEFE CONTROL PERDIDAS
J74: AUXILIAR FINANCIERO | Y74: JEFE BANCASEGUROS
J75: AUXILIAR CRÉDITO Y COBRANZA | Y75: JEFE AUTO
J76: AUXILIAR COSTOS | Y76: JEFE EMISIONES ARP
J77: AUXILIAR CONTABILIDAD | Y77: JEFE ESTUDIOS ACTUARIALES/ TÉCNICOS
J78: AUXILIAR CARTERA | Y78: JEFE COASEGUROS
J79: AUXILIAR FACTURACION | Y79: JEFE COASEGUROS
Y80: JEFE INDEMNIZACION
Y81: JEFE RECUPERACIONES
Y82: JEFE UNIDAD SUSCRIPCION
Y83: COORDINADOR SUSCRIPCIÓN
Y84: COORDINADOR TÉCNICO
Y85: JEFE SEGMENTO PYME
Y86: COORDINADOR PERSONAS
Y87: VALUADOR
Y88: JEFE CUENTAS CORRIENTES (SUCURSAL)
Y89: GERENTE OFICINA
Y90: SUBGERENTE ADMINISTRATIVO (SUCURSAL)
Y91: SUBGERENTE COMERCIAL (SUCURSAL)
... Y155: AUXILIAR EMISIONES ARP

Sheet Hoja4
C3: CATEGORIA | D3: RUTA CARRERA GERENCIAL | E3: RUTA CARRERA CONTRIBUCION INDIVIDUAL | F3: PISTA
C4: 25 | D4: Presidente Global | F4: =IF(D4="","",D4)&IF(OR(E4="",D4=""),""," / ")&E4 -> Presidente Global
C5: 24 | D5: Presidente Regional | F5: =IF(D5="","",D5)&IF(OR(E5="",D5=""),""," / ")&E5 -> Presidente Regional
C6: 23 | D6: Presidente Pais | F6: =IF(D6="","",D6)&IF(OR(E6="",D6=""),""," / ")&E6 -> Presidente Pais
C7: 22 | D7: Vicepresidente / Director Región / Presidente País | F7: =IF(D7="","",D7)&IF(OR(E7="",D7=""),""," / ")&E7 -> Vicepresidente / Director Región / Presidente País
C8: 21 | D8: Vicepresidente / Director Región / Presidente País | F8: =IF(D8="","",D8)&IF(OR(E8="",D8=""),""," / ")&E8 -> Vicepresidente / Director Región / Presidente País
C9: 20 | D9: Vicepresidente / Director Región / Presidente País | F9: =IF(D9="","",D9)&IF(OR(E9="",D9=""),""," / ")&E9 -> Vicepresidente / Director Región / Presidente País
C10: 19 | D10: Gerente / Gerente Región / Gerente País / Gerente Unidad de Negocio | F10: =IF(D10="","",D10)&IF(OR(E10="",D10=""),""," / ")&E10 -> Gerente / Gerente Región / Gerente País / Gerente Unidad de Negocio
C11: 18 | D11: Gerente / Gerente Región / Gerente País / Gerente Unidad de Negocio | E11: Gerente de Cuenta | F11: =IF(D11="","",D11)&IF(OR(E11="",D11=""),""," / ")&E11 -> Gerente / Gerente Región / Gerente País / Gerente Unidad de Negocio / Gerente de Cuenta
C12: 17 | D12: Gerente / Gerente Región / Gerente País / Gerente Unidad de Negocio | E12: Gerente de Cuenta | F12: =IF(D12="","",D12)&IF(OR(E12="",D12=""),""," / ")&E12 -> Gerente / Gerente Región / Gerente País / Gerente Unidad de Negocio / Gerente de Cuenta
C13: 16 | D13: Gerente / Gerente Región / Gerente País / Gerente Unidad de Negocio | E13: Gerente de Cuenta | F13: =IF(D13="","",D13)&IF(OR(E13="",D13=""),""," / ")&E13 -> Gerente / Gerente Región / Gerente País / Gerente Unidad de Negocio / Gerente de Cuenta
C14: 15 | D14: Director / Jefe | E14: Especialista Sr / Ingeniero / Ejecutivo de Cuenta | F14: =IF(D14="","",D14)&IF(OR(E14="",D14=""),""," / ")&E14 -> Director / Jefe / Especialista Sr / Ingeniero / Ejecutivo de Cuenta
C15: 14 | D15: Director / Jefe | E15: Especialista Sr / Ingeniero / Ejecutivo de Cuenta | F15: =IF(D15="","",D15)&IF(OR(E15="",D15=""),""," / ")&E15 -> Director / Jefe / Especialista Sr / Ingeniero / Ejecutivo de Cuenta
C16: 13 | D16: Director / Jefe | E16: Especialista Sr / Ingeniero / Ejecutivo de Cuenta | F16: =IF(D16="","",D16)&IF(OR(E16="",D16=""),""," / ")&E16 -> Director / Jefe / Especialista Sr / Ingeniero / Ejecutivo de Cuenta
C17: 12 | D17: Director / Jefe | E17: Especialista / Ingeniero / Ejecutivo de Cuenta | F17: =IF(D17="","",D17)&IF(OR(E17="",D17=""),""," / ")&E17 -> Director / Jefe / Especialista / Ingeniero / Ejecutivo de Cuenta
C18: 11 | D18: Coordinador | E18: Especialista / Ingeniero / Ejecutivo de Cuenta | F18: =IF(D18="","",D18)&IF(OR(E18="",D18=""),""," / ")&E18 -> Coordinador / Especialista / Ingeniero / Ejecutivo de Cuenta
C19: 10 | D19: Coordinador | E19: Especialista / Ingeniero / Ejecutivo de Cuenta | F19: =IF(D19="","",D19)&IF(OR(E19="",D19=""),""," / ")&E19 -> Coordinador / Especialista / Ingeniero / Ejecutivo de Cuenta
C20: 9 | D20: Coordinador | E20: Analista Sr / Ingeniero / Asesor Comercial | F20: =IF(D20="","",D20)&IF(OR(E20="",D20=""),""," / ")&E20 -> Coordinador / Analista Sr / Ingeniero / Asesor Comercial
C21: 8 | D21: Supervisor | E21: Analista Sr / Técnico / Operario Especializado / Ingeniero / Asesor Comercial | F21: =IF(D21="","",D21)&IF(OR(E21="",D21=""),""," / ")&E21 -> Supervisor / Analista Sr / Técnico / Operario Especializado / Ingeniero / Asesor Comercial
C22: 7 | D22: Supervisor | E22: Analista / Técnico / Operario Especializado / Ingeniero / Asesor Comercial | F22: =IF(D22="","",D22)&IF(OR(E22="",D22=""),""," / ")&E22 -> Supervisor / Analista / Técnico / Operario Especializado / Ingeniero / Asesor Comercial
C23: 6 | D23: Supervisor | E23: Analista / Técnico / Operario Especializado / Asesor Comercial | F23: =IF(D23="","",D23)&IF(OR(E23="",D23=""),""," / ")&E23 -> Supervisor / Analista / Técnico / Operario Especializado / Asesor Comercial
C24: 5 | E24: Auxiliar/Operario III / Representante de Ventas Sr | F24: =IF(D24="","",D24)&IF(OR(E24="",D24=""),""," / ")&E24 -> Auxiliar/Operario III / Representante de Ventas Sr
C25: 4 | E25: Auxiliar / Operario II / Representante de Ventas Sr | F25: =IF(D25="","",D25)&IF(OR(E25="",D25=""),""," / ")&E25 -> Auxiliar / Operario II / Representante de Ventas Sr
C26: 3 | E26: Auxiliar / Operario I / Representante de Ventas Jr | F26: =IF(D26="","",D26)&IF(OR(E26="",D26=""),""," / ")&E26 -> Auxiliar / Operario I / Representante de Ventas Jr
C27: 2 | E27: Auxiliar / Operario I / Representante de Ventas Jr | F27: =IF(D27="","",D27)&IF(OR(E27="",D27=""),""," / ")&E27 -> Auxiliar / Operario I / Representante de Ventas Jr
C28: 1 | E28: Operario I / Ayudante | F28: =IF(D28="","",D28)&IF(OR(E28="",D28=""),""," / ")&E28 -> Operario I / Ayudante
